{"rangeHash":[{"word":"وَإِذَا","translation":"And when","occurences":["2:231","2:232"]},{"word":"طَلَّقْتُمُ","translation":"you divorce","occurences":["2:231","2:232","2:236"]},{"word":"ٱلنِّسَآءَ","translation":"the women","occurences":["2:231","2:232","2:236"]},{"word":"فَبَلَغْنَ","translation":"and they reach","occurences":["2:231","2:232"]},{"word":"أَجَلَهُنَّ","translation":"their (waiting) term","occurences":["2:231","2:232","2:234"]},{"word":"فَأَمْسِكُوهُنَّ","translation":"then retain them","occurences":["2:231"]},{"word":"بِمَعْرُوفٍ","translation":"in a fair manner","occurences":["2:231"]},{"word":"أَوْ","translation":"or","occurences":["2:231","2:235","2:236","2:237","2:239"]},{"word":"سَرِّحُوهُنَّ","translation":"release them","occurences":["2:231"]},{"word":"بِمَعْرُوفٍۢ ۚ","translation":"in a fair manner","occurences":["2:231"]},{"word":"وَلَا","translation":"And (do) not","occurences":["2:231","2:231","2:233","2:235","2:235","2:237"]},{"word":"تُمْسِكُوهُنَّ","translation":"retain them","occurences":["2:231"]},{"word":"ضِرَارًۭا","translation":"(to) hurt","occurences":["2:231"]},{"word":"لِّتَعْتَدُوا۟ ۚ","translation":"so that you transgress","occurences":["2:231"]},{"word":"وَمَن","translation":"And whoever","occurences":["2:231","2:249"]},{"word":"يَفْعَلْ","translation":"does","occurences":["2:231"]},{"word":"ذَٰلِكَ","translation":"that","occurences":["2:231","2:232","2:248"]},{"word":"فَقَدْ","translation":"then indeed","occurences":["2:231"]},{"word":"ظَلَمَ","translation":"he wronged","occurences":["2:231"]},{"word":"نَفْسَهُۥ ۚ","translation":"himself","occurences":["2:231"]},{"word":"تَتَّخِذُوٓا۟","translation":"take","occurences":["2:231"]},{"word":"ءَايَـٰتِ","translation":"(the) Verses","occurences":["2:231"]},{"word":"ٱللَّهِ","translation":"(of) Allah","occurences":["2:231","2:231","2:244","2:246","2:249","2:251","2:251","2:252"]},{"word":"هُزُوًۭا ۚ","translation":"(in) jest","occurences":["2:231"]},{"word":"وَٱذْكُرُوا۟","translation":"and remember","occurences":["2:231"]},{"word":"نِعْمَتَ","translation":"(the) Favors","occurences":["2:231"]},{"word":"عَلَيْكُمْ","translation":"upon you","occurences":["2:231","2:233","2:234","2:235","2:236","2:240","2:247"]},{"word":"وَمَآ","translation":"and what","occurences":["2:231"]},{"word":"أَنزَلَ","translation":"(is) revealed","occurences":["2:231"]},{"word":"عَلَيْكُم","translation":"to you","occurences":["2:231"]},{"word":"مِّنَ","translation":"of","occurences":["2:231","2:247"]},{"word":"ٱلْكِتَـٰبِ","translation":"the Book","occurences":["2:231"]},{"word":"وَٱلْحِكْمَةِ","translation":"and [the] wisdom","occurences":["2:231"]},{"word":"يَعِظُكُم","translation":"He instructs you","occurences":["2:231"]},{"word":"بِهِۦ ۚ","translation":"with it","occurences":["2:231"]},{"word":"وَٱتَّقُوا۟","translation":"And fear","occurences":["2:231","2:233"]},{"word":"ٱللَّهَ","translation":"Allah","occurences":["2:231","2:231","2:233","2:233","2:235","2:235","2:237","2:239","2:243","2:244","2:245","2:247","2:247","2:249","2:251"]},{"word":"وَٱعْلَمُوٓا۟","translation":"and know","occurences":["2:231","2:233","2:235","2:235","2:244"]},{"word":"أَنَّ","translation":"that","occurences":["2:231","2:233","2:235","2:235","2:244"]},{"word":"بِكُلِّ","translation":"of every","occurences":["2:231"]},{"word":"شَىْءٍ","translation":"thing","occurences":["2:231"]},{"word":"عَلِيمٌۭ","translation":"All-Knower","occurences":["2:231","2:244","2:247"]},{"word":"فَلَا","translation":"then (do) not","occurences":["2:232","2:233","2:233","2:234","2:240"]},{"word":"تَعْضُلُوهُنَّ","translation":"hinder them","occurences":["2:232"]},{"word":"أَن","translation":"[that]","occurences":["2:232","2:233","2:233","2:235","2:237","2:237","2:248"]},{"word":"يَنكِحْنَ","translation":"(from) marrying","occurences":["2:232"]},{"word":"أَزْوَٰجَهُنَّ","translation":"their husbands","occurences":["2:232"]},{"word":"إِذَا","translation":"when","occurences":["2:232","2:233"]},{"word":"تَرَٰضَوْا۟","translation":"they agree","occurences":["2:232"]},{"word":"بَيْنَهُم","translation":"between themselves","occurences":["2:232"]},{"word":"بِٱلْمَعْرُوفِ ۗ","translation":"in a fair manner","occurences":["2:232","2:233","2:234"]},{"word":"يُوعَظُ","translation":"is admonished","occurences":["2:232"]},{"word":"بِهِۦ","translation":"with it","occurences":["2:232","2:235"]},{"word":"مَن","translation":"whoever","occurences":["2:232","2:247"]},{"word":"كَانَ","translation":"[is]","occurences":["2:232"]},{"word":"مِنكُمْ","translation":"among you","occurences":["2:232","2:234","2:240"]},{"word":"يُؤْمِنُ","translation":"believes","occurences":["2:232"]},{"word":"بِٱللَّهِ","translation":"in Allah","occurences":["2:232"]},{"word":"وَٱلْيَوْمِ","translation":"and the Day","occurences":["2:232"]},{"word":"ٱلْـَٔاخِرِ ۗ","translation":"[the] Last","occurences":["2:232"]},{"word":"ذَٰلِكُمْ","translation":"that","occurences":["2:232"]},{"word":"أَزْكَىٰ","translation":"(is) more virtuous","occurences":["2:232"]},{"word":"لَكُمْ","translation":"for you","occurences":["2:232","2:242","2:247"]},{"word":"وَأَطْهَرُ ۗ","translation":"and more purer","occurences":["2:232"]},{"word":"وَٱللَّهُ","translation":"And Allah","occurences":["2:232","2:234","2:240","2:245","2:246","2:247","2:247","2:249"]},{"word":"يَعْلَمُ","translation":"knows","occurences":["2:232","2:235"]},{"word":"وَأَنتُمْ","translation":"and you","occurences":["2:232"]},{"word":"لَا","translation":"(do) not","occurences":["2:232","2:233","2:233","2:243","2:249"]},{"word":"تَعْلَمُونَ","translation":"know","occurences":["2:232","2:239"]},{"word":"۞ وَٱلْوَٰلِدَٰتُ","translation":"And the mothers","occurences":["2:233"]},{"word":"يُرْضِعْنَ","translation":"shall suckle","occurences":["2:233"]},{"word":"أَوْلَـٰدَهُنَّ","translation":"their children","occurences":["2:233"]},{"word":"حَوْلَيْنِ","translation":"(for) two years","occurences":["2:233"]},{"word":"كَامِلَيْنِ ۖ","translation":"complete","occurences":["2:233"]},{"word":"لِمَنْ","translation":"for whoever","occurences":["2:233"]},{"word":"أَرَادَ","translation":"wishes","occurences":["2:233"]},{"word":"يُتِمَّ","translation":"complete","occurences":["2:233"]},{"word":"ٱلرَّضَاعَةَ ۚ","translation":"the suckling","occurences":["2:233"]},{"word":"وَعَلَى","translation":"And upon","occurences":["2:233","2:233","2:236"]},{"word":"ٱلْمَوْلُودِ","translation":"the father","occurences":["2:233"]},{"word":"لَهُۥ","translation":"(on) him","occurences":["2:233"]},{"word":"رِزْقُهُنَّ","translation":"(is) their provision","occurences":["2:233"]},{"word":"وَكِسْوَتُهُنَّ","translation":"and their clothing","occurences":["2:233"]},{"word":"بِٱلْمَعْرُوفِ ۚ","translation":"in a fair manner","occurences":["2:233"]},{"word":"تُكَلَّفُ","translation":"is burdened","occurences":["2:233"]},{"word":"نَفْسٌ","translation":"any soul","occurences":["2:233"]},{"word":"إِلَّا","translation":"except","occurences":["2:233","2:246","2:249","2:249"]},{"word":"وُسْعَهَا ۚ","translation":"its capacity","occurences":["2:233"]},{"word":"تُضَآرَّ","translation":"made to suffer","occurences":["2:233"]},{"word":"وَٰلِدَةٌۢ","translation":"(the) mother","occurences":["2:233"]},{"word":"بِوَلَدِهَا","translation":"because of her child","occurences":["2:233"]},{"word":"مَوْلُودٌۭ","translation":"(the) father","occurences":["2:233"]},{"word":"لَّهُۥ","translation":"(be)","occurences":["2:233"]},{"word":"بِوَلَدِهِۦ ۚ","translation":"because of his child","occurences":["2:233"]},{"word":"ٱلْوَارِثِ","translation":"the (father's) heir","occurences":["2:233"]},{"word":"مِثْلُ","translation":"(is a duty) like","occurences":["2:233"]},{"word":"ذَٰلِكَ ۗ","translation":"that (of the father)","occurences":["2:233"]},{"word":"فَإِنْ","translation":"Then if","occurences":["2:233","2:239","2:240"]},{"word":"أَرَادَا","translation":"they both desire","occurences":["2:233"]},{"word":"فِصَالًا","translation":"weaning","occurences":["2:233"]},{"word":"عَن","translation":"through","occurences":["2:233"]},{"word":"تَرَاضٍۢ","translation":"mutual consent","occurences":["2:233"]},{"word":"مِّنْهُمَا","translation":"of both of them","occurences":["2:233"]},{"word":"وَتَشَاوُرٍۢ","translation":"and consultation","occurences":["2:233"]},{"word":"جُنَاحَ","translation":"blame","occurences":["2:233","2:233","2:234","2:235","2:236","2:240"]},{"word":"عَلَيْهِمَا ۗ","translation":"on both of them","occurences":["2:233"]},{"word":"وَإِنْ","translation":"And if","occurences":["2:233"]},{"word":"أَرَدتُّمْ","translation":"you want","occurences":["2:233"]},{"word":"تَسْتَرْضِعُوٓا۟","translation":"ask another women to suckle","occurences":["2:233"]},{"word":"أَوْلَـٰدَكُمْ","translation":"your child","occurences":["2:233"]},{"word":"سَلَّمْتُم","translation":"you pay","occurences":["2:233"]},{"word":"مَّآ","translation":"what","occurences":["2:233"]},{"word":"ءَاتَيْتُم","translation":"you give","occurences":["2:233"]},{"word":"بِمَا","translation":"of what","occurences":["2:233","2:234","2:237"]},{"word":"تَعْمَلُونَ","translation":"you do","occurences":["2:233","2:234","2:237"]},{"word":"بَصِيرٌۭ","translation":"(is) All-Seer","occurences":["2:233"]},{"word":"وَٱلَّذِينَ","translation":"And those who","occurences":["2:234","2:240","2:249"]},{"word":"يُتَوَفَّوْنَ","translation":"pass away","occurences":["2:234","2:240"]},{"word":"وَيَذَرُونَ","translation":"and leave behind","occurences":["2:234","2:240"]},{"word":"أَزْوَٰجًۭا","translation":"wives","occurences":["2:234","2:240"]},{"word":"يَتَرَبَّصْنَ","translation":"(the widows) should wait","occurences":["2:234"]},{"word":"بِأَنفُسِهِنَّ","translation":"for themselves","occurences":["2:234"]},{"word":"أَرْبَعَةَ","translation":"(for) four","occurences":["2:234"]},{"word":"أَشْهُرٍۢ","translation":"months","occurences":["2:234"]},{"word":"وَعَشْرًۭا ۖ","translation":"and ten (days)","occurences":["2:234"]},{"word":"فَإِذَا","translation":"Then when","occurences":["2:234"]},{"word":"بَلَغْنَ","translation":"they reach","occurences":["2:234"]},{"word":"فِيمَا","translation":"for what","occurences":["2:234","2:235"]},{"word":"فَعَلْنَ","translation":"they do","occurences":["2:234","2:240"]},{"word":"فِىٓ","translation":"concerning","occurences":["2:234","2:235","2:235","2:240"]},{"word":"أَنفُسِهِنَّ","translation":"themselves","occurences":["2:234","2:240"]},{"word":"خَبِيرٌۭ","translation":"(is) All-Aware","occurences":["2:234"]},{"word":"عَرَّضْتُم","translation":"you hint","occurences":["2:235"]},{"word":"مِنْ","translation":"of","occurences":["2:235"]},{"word":"خِطْبَةِ","translation":"marriage proposal","occurences":["2:235"]},{"word":"ٱلنِّسَآءِ","translation":"[to] the women","occurences":["2:235"]},{"word":"أَكْنَنتُمْ","translation":"you conceal it","occurences":["2:235"]},{"word":"أَنفُسِكُمْ ۚ","translation":"yourselves","occurences":["2:235"]},{"word":"عَلِمَ","translation":"Knows","occurences":["2:235"]},{"word":"ٱللَّهُ","translation":"Allah","occurences":["2:235","2:242","2:243","2:251"]},{"word":"أَنَّكُمْ","translation":"that you","occurences":["2:235"]},{"word":"سَتَذْكُرُونَهُنَّ","translation":"will mention them","occurences":["2:235"]},{"word":"وَلَـٰكِن","translation":"[and] but","occurences":["2:235"]},{"word":"لَّا","translation":"(do) not","occurences":["2:235","2:236"]},{"word":"تُوَاعِدُوهُنَّ","translation":"promise them (widows)","occurences":["2:235"]},{"word":"سِرًّا","translation":"secretly","occurences":["2:235"]},{"word":"إِلَّآ","translation":"except","occurences":["2:235","2:237"]},{"word":"تَقُولُوا۟","translation":"you say","occurences":["2:235"]},{"word":"قَوْلًۭا","translation":"a saying","occurences":["2:235"]},{"word":"مَّعْرُوفًۭا ۚ","translation":"honorable","occurences":["2:235"]},{"word":"تَعْزِمُوا۟","translation":"resolve (on)","occurences":["2:235"]},{"word":"عُقْدَةَ","translation":"the knot","occurences":["2:235"]},{"word":"ٱلنِّكَاحِ","translation":"(of) marriage","occurences":["2:235"]},{"word":"حَتَّىٰ","translation":"until","occurences":["2:235"]},{"word":"يَبْلُغَ","translation":"reaches","occurences":["2:235"]},{"word":"ٱلْكِتَـٰبُ","translation":"the prescribed term","occurences":["2:235"]},{"word":"أَجَلَهُۥ ۚ","translation":"its end","occurences":["2:235"]},{"word":"مَا","translation":"what","occurences":["2:235","2:236","2:237","2:240"]},{"word":"أَنفُسِكُمْ","translation":"yourselves","occurences":["2:235"]},{"word":"فَٱحْذَرُوهُ ۚ","translation":"so beware of Him","occurences":["2:235"]},{"word":"غَفُورٌ","translation":"(is) Oft-Forgiving","occurences":["2:235"]},{"word":"حَلِيمٌۭ","translation":"Most Forbearing","occurences":["2:235"]},{"word":"إِن","translation":"if","occurences":["2:236","2:246","2:248"]},{"word":"لَمْ","translation":"not","occurences":["2:236","2:239"]},{"word":"تَمَسُّوهُنَّ","translation":"you have touched","occurences":["2:236","2:237"]},{"word":"تَفْرِضُوا۟","translation":"you specified","occurences":["2:236"]},{"word":"لَهُنَّ","translation":"for them","occurences":["2:236","2:237"]},{"word":"فَرِيضَةًۭ ۚ","translation":"an obligation (dower)","occurences":["2:236"]},{"word":"وَمَتِّعُوهُنَّ","translation":"And make provision for them ","occurences":["2:236"]},{"word":"عَلَى","translation":"upon","occurences":["2:236","2:236","2:238","2:241","2:243","2:250","2:251"]},{"word":"ٱلْمُوسِعِ","translation":"the wealthy","occurences":["2:236"]},{"word":"قَدَرُهُۥ","translation":"according to his means","occurences":["2:236","2:236"]},{"word":"ٱلْمُقْتِرِ","translation":"the poor","occurences":["2:236"]},{"word":"مَتَـٰعًۢا","translation":"a provision","occurences":["2:236"]},{"word":"بِٱلْمَعْرُوفِ ۖ","translation":"in a fair manner","occurences":["2:236","2:241"]},{"word":"حَقًّا","translation":"a duty","occurences":["2:236","2:241"]},{"word":"ٱلْمُحْسِنِينَ","translation":"the good-doers","occurences":["2:236"]},{"word":"وَإِن","translation":"And if","occurences":["2:237"]},{"word":"طَلَّقْتُمُوهُنَّ","translation":"you divorce them","occurences":["2:237"]},{"word":"مِن","translation":"from","occurences":["2:237","2:240","2:243","2:246"]},{"word":"قَبْلِ","translation":"before","occurences":["2:237"]},{"word":"وَقَدْ","translation":"while already","occurences":["2:237","2:246"]},{"word":"فَرَضْتُمْ","translation":"you have specified","occurences":["2:237","2:237"]},{"word":"فَرِيضَةًۭ","translation":"an obligation (dower)","occurences":["2:237"]},{"word":"فَنِصْفُ","translation":"then (give) half","occurences":["2:237"]},{"word":"يَعْفُونَ","translation":"they (women) forgo (it)","occurences":["2:237"]},{"word":"يَعْفُوَا۟","translation":"forgoes","occurences":["2:237"]},{"word":"ٱلَّذِى","translation":"the one","occurences":["2:237","2:245"]},{"word":"بِيَدِهِۦ","translation":"in whose hands","occurences":["2:237"]},{"word":"عُقْدَةُ","translation":"(is the) knot","occurences":["2:237"]},{"word":"ٱلنِّكَاحِ ۚ","translation":"(of) the marriage","occurences":["2:237"]},{"word":"وَأَن","translation":"And that","occurences":["2:237"]},{"word":"تَعْفُوٓا۟","translation":"you forgo","occurences":["2:237"]},{"word":"أَقْرَبُ","translation":"(is) nearer","occurences":["2:237"]},{"word":"لِلتَّقْوَىٰ ۚ","translation":"to [the] righteousness","occurences":["2:237"]},{"word":"تَنسَوُا۟","translation":"forget","occurences":["2:237"]},{"word":"ٱلْفَضْلَ","translation":"the graciousness","occurences":["2:237"]},{"word":"بَيْنَكُمْ ۚ","translation":"among you","occurences":["2:237"]},{"word":"إِنَّ","translation":"Indeed","occurences":["2:237","2:243","2:247","2:247","2:248","2:248","2:249"]},{"word":"بَصِيرٌ","translation":"(is) All-Seer","occurences":["2:237"]},{"word":"حَـٰفِظُوا۟","translation":"Guard strictly","occurences":["2:238"]},{"word":"ٱلصَّلَوَٰتِ","translation":"the prayers","occurences":["2:238"]},{"word":"وَٱلصَّلَوٰةِ","translation":"and the prayer ","occurences":["2:238"]},{"word":"ٱلْوُسْطَىٰ","translation":"[the] middle","occurences":["2:238"]},{"word":"وَقُومُوا۟","translation":"and stand up","occurences":["2:238"]},{"word":"لِلَّهِ","translation":"for Allah","occurences":["2:238"]},{"word":"قَـٰنِتِينَ","translation":"devoutly obedient","occurences":["2:238"]},{"word":"خِفْتُمْ","translation":"you fear","occurences":["2:239"]},{"word":"فَرِجَالًا","translation":"then (pray) on foot","occurences":["2:239"]},{"word":"رُكْبَانًۭا ۖ","translation":"riding","occurences":["2:239"]},{"word":"فَإِذَآ","translation":"Then when","occurences":["2:239"]},{"word":"أَمِنتُمْ","translation":"you are secure","occurences":["2:239"]},{"word":"فَٱذْكُرُوا۟","translation":"then remember","occurences":["2:239"]},{"word":"كَمَا","translation":"as","occurences":["2:239"]},{"word":"عَلَّمَكُم","translation":"He (has) taught you","occurences":["2:239"]},{"word":"مَّا","translation":"what","occurences":["2:239"]},{"word":"تَكُونُوا۟","translation":"you were","occurences":["2:239"]},{"word":"وَصِيَّةًۭ","translation":"(should make) a will","occurences":["2:240"]},{"word":"لِّأَزْوَٰجِهِم","translation":"for their wives","occurences":["2:240"]},{"word":"مَّتَـٰعًا","translation":"provision","occurences":["2:240"]},{"word":"إِلَى","translation":"for","occurences":["2:240","2:243","2:246"]},{"word":"ٱلْحَوْلِ","translation":"the year","occurences":["2:240"]},{"word":"غَيْرَ","translation":"without","occurences":["2:240"]},{"word":"إِخْرَاجٍۢ ۚ","translation":"driving (them) out","occurences":["2:240"]},{"word":"خَرَجْنَ","translation":"they leave","occurences":["2:240"]},{"word":"فِى","translation":"in","occurences":["2:240","2:244","2:246","2:246","2:247","2:248"]},{"word":"مَّعْرُوفٍۢ ۗ","translation":"honorably","occurences":["2:240"]},{"word":"عَزِيزٌ","translation":"(is) All-Mighty","occurences":["2:240"]},{"word":"حَكِيمٌۭ","translation":"All-Wise","occurences":["2:240"]},{"word":"وَلِلْمُطَلَّقَـٰتِ","translation":"And for the divorced women","occurences":["2:241"]},{"word":"مَتَـٰعٌۢ","translation":"(is) a provision","occurences":["2:241"]},{"word":"ٱلْمُتَّقِينَ","translation":"the righteous","occurences":["2:241"]},{"word":"كَذَٰلِكَ","translation":"Thus","occurences":["2:242"]},{"word":"يُبَيِّنُ","translation":"makes clear","occurences":["2:242"]},{"word":"ءَايَـٰتِهِۦ","translation":"His Verses","occurences":["2:242"]},{"word":"لَعَلَّكُمْ","translation":"so that you may","occurences":["2:242"]},{"word":"تَعْقِلُونَ","translation":"use your intellect","occurences":["2:242"]},{"word":"۞ أَلَمْ","translation":"Did not","occurences":["2:243"]},{"word":"تَرَ","translation":"you see","occurences":["2:243","2:246"]},{"word":"ٱلَّذِينَ","translation":"those who","occurences":["2:243","2:249"]},{"word":"خَرَجُوا۟","translation":"went out","occurences":["2:243"]},{"word":"دِيَـٰرِهِمْ","translation":"their homes","occurences":["2:243"]},{"word":"وَهُمْ","translation":"and they","occurences":["2:243"]},{"word":"أُلُوفٌ","translation":"(were in) thousands","occurences":["2:243"]},{"word":"حَذَرَ","translation":"(in) fear","occurences":["2:243"]},{"word":"ٱلْمَوْتِ","translation":"(of) [the] death","occurences":["2:243"]},{"word":"فَقَالَ","translation":"Then said","occurences":["2:243"]},{"word":"لَهُمُ","translation":"to them","occurences":["2:243"]},{"word":"مُوتُوا۟","translation":"Die","occurences":["2:243"]},{"word":"ثُمَّ","translation":"then","occurences":["2:243"]},{"word":"أَحْيَـٰهُمْ ۚ","translation":"He restored them to life","occurences":["2:243"]},{"word":"لَذُو","translation":"(is) surely Possessor","occurences":["2:243"]},{"word":"فَضْلٍ","translation":"(of) bounty","occurences":["2:243","2:251"]},{"word":"ٱلنَّاسِ","translation":"[the] mankind","occurences":["2:243","2:243"]},{"word":"وَلَـٰكِنَّ","translation":"[and] but","occurences":["2:243","2:251"]},{"word":"أَكْثَرَ","translation":"most","occurences":["2:243"]},{"word":"يَشْكُرُونَ","translation":"grateful","occurences":["2:243"]},{"word":"وَقَـٰتِلُوا۟","translation":"And fight","occurences":["2:244"]},{"word":"سَبِيلِ","translation":"(the) way","occurences":["2:244","2:246","2:246"]},{"word":"سَمِيعٌ","translation":"(is) All-Hearing","occurences":["2:244"]},{"word":"مَّن","translation":"Who","occurences":["2:245"]},{"word":"ذَا","translation":"(is) the one","occurences":["2:245"]},{"word":"يُقْرِضُ","translation":"will lend","occurences":["2:245"]},{"word":"قَرْضًا","translation":"a loan","occurences":["2:245"]},{"word":"حَسَنًۭا","translation":"good","occurences":["2:245"]},{"word":"فَيُضَـٰعِفَهُۥ","translation":"so (that) He multiplies it","occurences":["2:245"]},{"word":"لَهُۥٓ","translation":"for him ","occurences":["2:245"]},{"word":"أَضْعَافًۭا","translation":"manifolds","occurences":["2:245"]},{"word":"كَثِيرَةًۭ ۚ","translation":"many","occurences":["2:245"]},{"word":"يَقْبِضُ","translation":"withholds","occurences":["2:245"]},{"word":"وَيَبْصُۜطُ","translation":"and grants abundance","occurences":["2:245"]},{"word":"وَإِلَيْهِ","translation":"and to Him","occurences":["2:245"]},{"word":"تُرْجَعُونَ","translation":"you will be returned","occurences":["2:245"]},{"word":"أَلَمْ","translation":"Did not","occurences":["2:246"]},{"word":"ٱلْمَلَإِ","translation":"the chiefs","occurences":["2:246"]},{"word":"مِنۢ","translation":"of","occurences":["2:246","2:246"]},{"word":"بَنِىٓ","translation":"(the) Children","occurences":["2:246"]},{"word":"إِسْرَٰٓءِيلَ","translation":"(of) Israel","occurences":["2:246"]},{"word":"بَعْدِ","translation":"after","occurences":["2:246"]},{"word":"مُوسَىٰٓ","translation":"Musa","occurences":["2:246"]},{"word":"إِذْ","translation":"when","occurences":["2:246"]},{"word":"قَالُوا۟","translation":"they said","occurences":["2:246","2:246","2:249","2:250"]},{"word":"لِنَبِىٍّۢ","translation":"to a Prophet","occurences":["2:246"]},{"word":"لَّهُمُ","translation":"of theirs","occurences":["2:246"]},{"word":"ٱبْعَثْ","translation":"Appoint","occurences":["2:246"]},{"word":"لَنَا","translation":"for us","occurences":["2:246","2:249"]},{"word":"مَلِكًۭا","translation":"a king","occurences":["2:246"]},{"word":"نُّقَـٰتِلْ","translation":"we may fight","occurences":["2:246"]},{"word":"ٱللَّهِ ۖ","translation":"(of) Allah","occurences":["2:246"]},{"word":"قَالَ","translation":"He said","occurences":["2:246","2:247","2:249","2:249"]},{"word":"هَلْ","translation":"Would","occurences":["2:246"]},{"word":"عَسَيْتُمْ","translation":"you perhaps ","occurences":["2:246"]},{"word":"كُتِبَ","translation":"prescribed","occurences":["2:246","2:246"]},{"word":"عَلَيْكُمُ","translation":"upon you","occurences":["2:246"]},{"word":"ٱلْقِتَالُ","translation":"[the] fighting","occurences":["2:246","2:246"]},{"word":"أَلَّا","translation":"that not","occurences":["2:246","2:246"]},{"word":"تُقَـٰتِلُوا۟ ۖ","translation":"you fight","occurences":["2:246"]},{"word":"وَمَا","translation":"And what","occurences":["2:246"]},{"word":"لَنَآ","translation":"for us","occurences":["2:246"]},{"word":"نُقَـٰتِلَ","translation":"we fight","occurences":["2:246"]},{"word":"أُخْرِجْنَا","translation":"we have been driven","occurences":["2:246"]},{"word":"دِيَـٰرِنَا","translation":"our homes","occurences":["2:246"]},{"word":"وَأَبْنَآئِنَا ۖ","translation":"and our children","occurences":["2:246"]},{"word":"فَلَمَّا","translation":"Yet, when","occurences":["2:246","2:249","2:249"]},{"word":"عَلَيْهِمُ","translation":"upon them","occurences":["2:246"]},{"word":"تَوَلَّوْا۟","translation":"they turned away","occurences":["2:246"]},{"word":"قَلِيلًۭا","translation":"a few","occurences":["2:246","2:249"]},{"word":"مِّنْهُمْ ۗ","translation":"among them","occurences":["2:246"]},{"word":"عَلِيمٌۢ","translation":"(is) All-Knowing","occurences":["2:246"]},{"word":"بِٱلظَّـٰلِمِينَ","translation":"of the wrongdoers","occurences":["2:246"]},{"word":"وَقَالَ","translation":"And said","occurences":["2:247","2:248"]},{"word":"لَهُمْ","translation":"to them","occurences":["2:247","2:248"]},{"word":"نَبِيُّهُمْ","translation":"their Prophet","occurences":["2:247","2:248"]},{"word":"قَدْ","translation":"(has) surely","occurences":["2:247"]},{"word":"بَعَثَ","translation":"raised","occurences":["2:247"]},{"word":"طَالُوتَ","translation":"Talut","occurences":["2:247"]},{"word":"مَلِكًۭا ۚ","translation":"(as) a king","occurences":["2:247"]},{"word":"قَالُوٓا۟","translation":"They said","occurences":["2:247"]},{"word":"أَنَّىٰ","translation":"How","occurences":["2:247"]},{"word":"يَكُونُ","translation":"can be","occurences":["2:247"]},{"word":"لَهُ","translation":"for him","occurences":["2:247"]},{"word":"ٱلْمُلْكُ","translation":"the kingship","occurences":["2:247"]},{"word":"عَلَيْنَا","translation":"over us","occurences":["2:247","2:250"]},{"word":"وَنَحْنُ","translation":"while we","occurences":["2:247"]},{"word":"أَحَقُّ","translation":"(are) more entitled","occurences":["2:247"]},{"word":"بِٱلْمُلْكِ","translation":"to kingship","occurences":["2:247"]},{"word":"مِنْهُ","translation":"than him","occurences":["2:247","2:249","2:249"]},{"word":"وَلَمْ","translation":"and not","occurences":["2:247"]},{"word":"يُؤْتَ","translation":"he has been given","occurences":["2:247"]},{"word":"سَعَةًۭ","translation":"abundance","occurences":["2:247"]},{"word":"ٱلْمَالِ ۚ","translation":"[the] wealth","occurences":["2:247"]},{"word":"ٱصْطَفَىٰهُ","translation":"has chosen him","occurences":["2:247"]},{"word":"وَزَادَهُۥ","translation":"and increased him","occurences":["2:247"]},{"word":"بَسْطَةًۭ","translation":"abundantly","occurences":["2:247"]},{"word":"ٱلْعِلْمِ","translation":"[the] knowledge","occurences":["2:247"]},{"word":"وَٱلْجِسْمِ ۖ","translation":"and [the] physique","occurences":["2:247"]},{"word":"يُؤْتِى","translation":"gives","occurences":["2:247"]},{"word":"مُلْكَهُۥ","translation":"His kingdom","occurences":["2:247"]},{"word":"يَشَآءُ ۚ","translation":"He wills","occurences":["2:247"]},{"word":"وَٰسِعٌ","translation":"(is) All-Encompassing","occurences":["2:247"]},{"word":"ءَايَةَ","translation":"a sign","occurences":["2:248"]},{"word":"مُلْكِهِۦٓ","translation":"(of) his kingship","occurences":["2:248"]},{"word":"يَأْتِيَكُمُ","translation":"will come to you","occurences":["2:248"]},{"word":"ٱلتَّابُوتُ","translation":"the ark","occurences":["2:248"]},{"word":"فِيهِ","translation":"in it","occurences":["2:248"]},{"word":"سَكِينَةٌۭ","translation":"(is) tranquility","occurences":["2:248"]},{"word":"مِّن","translation":"from","occurences":["2:248","2:249"]},{"word":"رَّبِّكُمْ","translation":"your Lord","occurences":["2:248"]},{"word":"وَبَقِيَّةٌۭ","translation":"and a remnant","occurences":["2:248"]},{"word":"مِّمَّا","translation":"of what","occurences":["2:248"]},{"word":"تَرَكَ","translation":"(was) left","occurences":["2:248"]},{"word":"ءَالُ","translation":"(by the) family","occurences":["2:248"]},{"word":"مُوسَىٰ","translation":"(of) Musa","occurences":["2:248"]},{"word":"وَءَالُ","translation":"and family","occurences":["2:248"]},{"word":"هَـٰرُونَ","translation":"(of) Harun","occurences":["2:248"]},{"word":"تَحْمِلُهُ","translation":"will carry it","occurences":["2:248"]},{"word":"ٱلْمَلَـٰٓئِكَةُ ۚ","translation":"the Angels","occurences":["2:248"]},{"word":"لَـَٔايَةًۭ","translation":"(is) surely a sign","occurences":["2:248"]},{"word":"لَّكُمْ","translation":"for you","occurences":["2:248"]},{"word":"كُنتُم","translation":"you are","occurences":["2:248"]},{"word":"مُّؤْمِنِينَ","translation":"believers","occurences":["2:248"]},{"word":"فَصَلَ","translation":"set out","occurences":["2:249"]},{"word":"طَالُوتُ","translation":"Talut","occurences":["2:249"]},{"word":"بِٱلْجُنُودِ","translation":"with the forces","occurences":["2:249"]},{"word":"مُبْتَلِيكُم","translation":"will test you","occurences":["2:249"]},{"word":"بِنَهَرٍۢ","translation":"with a river","occurences":["2:249"]},{"word":"فَمَن","translation":"So whoever","occurences":["2:249"]},{"word":"شَرِبَ","translation":"drinks","occurences":["2:249"]},{"word":"فَلَيْسَ","translation":"then he is not","occurences":["2:249"]},{"word":"مِنِّى","translation":"from me","occurences":["2:249"]},{"word":"لَّمْ","translation":"(does) not","occurences":["2:249"]},{"word":"يَطْعَمْهُ","translation":"taste it","occurences":["2:249"]},{"word":"فَإِنَّهُۥ","translation":"then indeed, he","occurences":["2:249"]},{"word":"مِنِّىٓ","translation":"(is) from me","occurences":["2:249"]},{"word":"مَنِ","translation":"whoever","occurences":["2:249"]},{"word":"ٱغْتَرَفَ","translation":"takes","occurences":["2:249"]},{"word":"غُرْفَةًۢ","translation":"(in the) hollow","occurences":["2:249"]},{"word":"بِيَدِهِۦ ۚ","translation":"(of) his hand","occurences":["2:249"]},{"word":"فَشَرِبُوا۟","translation":"Then they drank","occurences":["2:249"]},{"word":"مِّنْهُمْ ۚ","translation":"of them","occurences":["2:249"]},{"word":"جَاوَزَهُۥ","translation":"he crossed it","occurences":["2:249"]},{"word":"هُوَ","translation":"he","occurences":["2:249"]},{"word":"ءَامَنُوا۟","translation":"believed","occurences":["2:249"]},{"word":"مَعَهُۥ","translation":"with him","occurences":["2:249"]},{"word":"طَاقَةَ","translation":"strength","occurences":["2:249"]},{"word":"ٱلْيَوْمَ","translation":"today","occurences":["2:249"]},{"word":"بِجَالُوتَ","translation":"against Jalut","occurences":["2:249"]},{"word":"وَجُنُودِهِۦ ۚ","translation":"and his troops","occurences":["2:249"]},{"word":"يَظُنُّونَ","translation":"were certain","occurences":["2:249"]},{"word":"أَنَّهُم","translation":"that they","occurences":["2:249"]},{"word":"مُّلَـٰقُوا۟","translation":"(would) meet","occurences":["2:249"]},{"word":"كَم","translation":"How many","occurences":["2:249"]},{"word":"فِئَةٍۢ","translation":"a company","occurences":["2:249"]},{"word":"قَلِيلَةٍ","translation":"small","occurences":["2:249"]},{"word":"غَلَبَتْ","translation":"overcame","occurences":["2:249"]},{"word":"فِئَةًۭ","translation":"a company","occurences":["2:249"]},{"word":"كَثِيرَةًۢ","translation":"large","occurences":["2:249"]},{"word":"بِإِذْنِ","translation":"by (the) permission","occurences":["2:249","2:251"]},{"word":"ٱللَّهِ ۗ","translation":"(of) Allah","occurences":["2:249"]},{"word":"مَعَ","translation":"(is) with","occurences":["2:249"]},{"word":"ٱلصَّـٰبِرِينَ","translation":"the patient ones","occurences":["2:249"]},{"word":"وَلَمَّا","translation":"And when","occurences":["2:250"]},{"word":"بَرَزُوا۟","translation":"they went forth","occurences":["2:250"]},{"word":"لِجَالُوتَ","translation":"to (face) Jalut","occurences":["2:250"]},{"word":"وَجُنُودِهِۦ","translation":"and his troops","occurences":["2:250"]},{"word":"رَبَّنَآ","translation":"Our Lord","occurences":["2:250"]},{"word":"أَفْرِغْ","translation":"Pour","occurences":["2:250"]},{"word":"صَبْرًۭا","translation":"patience","occurences":["2:250"]},{"word":"وَثَبِّتْ","translation":"and make firm","occurences":["2:250"]},{"word":"أَقْدَامَنَا","translation":"our feet","occurences":["2:250"]},{"word":"وَٱنصُرْنَا","translation":"and help us","occurences":["2:250"]},{"word":"ٱلْقَوْمِ","translation":"the people","occurences":["2:250"]},{"word":"ٱلْكَـٰفِرِينَ","translation":"(who are) disbelieving","occurences":["2:250"]},{"word":"فَهَزَمُوهُم","translation":"So they defeated them","occurences":["2:251"]},{"word":"وَقَتَلَ","translation":"and killed","occurences":["2:251"]},{"word":"دَاوُۥدُ","translation":"Dawood","occurences":["2:251"]},{"word":"جَالُوتَ","translation":"Jalut","occurences":["2:251"]},{"word":"وَءَاتَىٰهُ","translation":"and gave him","occurences":["2:251"]},{"word":"ٱلْمُلْكَ","translation":"the kingdom","occurences":["2:251"]},{"word":"وَٱلْحِكْمَةَ","translation":"and the wisdom","occurences":["2:251"]},{"word":"وَعَلَّمَهُۥ","translation":"and taught him","occurences":["2:251"]},{"word":"مِمَّا","translation":"that which","occurences":["2:251"]},{"word":"يَشَآءُ ۗ","translation":"He willed","occurences":["2:251"]},{"word":"وَلَوْلَا","translation":"And if not","occurences":["2:251"]},{"word":"دَفْعُ","translation":"(for the) repelling","occurences":["2:251"]},{"word":"ٱلنَّاسَ","translation":"[the] people ","occurences":["2:251"]},{"word":"بَعْضَهُم","translation":"some of them","occurences":["2:251"]},{"word":"بِبَعْضٍۢ","translation":"with others","occurences":["2:251"]},{"word":"لَّفَسَدَتِ","translation":"certainly (would have) corrupted","occurences":["2:251"]},{"word":"ٱلْأَرْضُ","translation":"the Earth","occurences":["2:251"]},{"word":"ذُو","translation":"(is) Possessor","occurences":["2:251"]},{"word":"ٱلْعَـٰلَمِينَ","translation":"the worlds","occurences":["2:251"]},{"word":"تِلْكَ","translation":"These","occurences":["2:252"]},{"word":"ءَايَـٰتُ","translation":"(are the) Verses","occurences":["2:252"]},{"word":"نَتْلُوهَا","translation":"We recite them","occurences":["2:252"]},{"word":"عَلَيْكَ","translation":"to you","occurences":["2:252"]},{"word":"بِٱلْحَقِّ ۚ","translation":"in [the] truth","occurences":["2:252"]},{"word":"وَإِنَّكَ","translation":"And indeed, you","occurences":["2:252"]},{"word":"لَمِنَ","translation":"(are) surely of","occurences":["2:252"]},{"word":"ٱلْمُرْسَلِينَ","translation":"the Messengers","occurences":["2:252"]}],"wordCount":440}