{"rangeHash":[{"word":"۞ لَّا","translation":"(There is) no","occurences":["4:114"]},{"word":"خَيْرَ","translation":"good","occurences":["4:114"]},{"word":"فِى","translation":"in","occurences":["4:114","4:126","4:126","4:127","4:127","4:127","4:131","4:131","4:131","4:131","4:132","4:132","4:140","4:140","4:140","4:145"]},{"word":"كَثِيرٍۢ","translation":"much","occurences":["4:114"]},{"word":"مِّن","translation":"of","occurences":["4:114","4:119","4:130"]},{"word":"نَّجْوَىٰهُمْ","translation":"their secret talk","occurences":["4:114"]},{"word":"إِلَّا","translation":"except","occurences":["4:114","4:117","4:120","4:142","4:146"]},{"word":"مَنْ","translation":"(he) who","occurences":["4:114"]},{"word":"أَمَرَ","translation":"orders","occurences":["4:114"]},{"word":"بِصَدَقَةٍ","translation":"charity","occurences":["4:114"]},{"word":"أَوْ","translation":"or","occurences":["4:114","4:114","4:124","4:128","4:135","4:135"]},{"word":"مَعْرُوفٍ","translation":"kindness","occurences":["4:114"]},{"word":"إِصْلَـٰحٍۭ","translation":"conciliation","occurences":["4:114"]},{"word":"بَيْنَ","translation":"between","occurences":["4:114","4:129","4:143"]},{"word":"ٱلنَّاسِ ۚ","translation":"the people","occurences":["4:114"]},{"word":"وَمَن","translation":"And who","occurences":["4:114","4:115","4:116","4:119","4:124","4:136","4:143"]},{"word":"يَفْعَلْ","translation":"does","occurences":["4:114"]},{"word":"ذَٰلِكَ","translation":"that","occurences":["4:114","4:116","4:133","4:143"]},{"word":"ٱبْتِغَآءَ","translation":"seeking","occurences":["4:114"]},{"word":"مَرْضَاتِ","translation":"pleasure","occurences":["4:114"]},{"word":"ٱللَّهِ","translation":"(of) Allah","occurences":["4:114","4:119","4:122","4:122","4:123","4:134","4:140","4:141"]},{"word":"فَسَوْفَ","translation":"then soon","occurences":["4:114"]},{"word":"نُؤْتِيهِ","translation":"We will give him","occurences":["4:114"]},{"word":"أَجْرًا","translation":"a reward","occurences":["4:114","4:146"]},{"word":"عَظِيمًۭا","translation":"great","occurences":["4:114","4:146"]},{"word":"يُشَاقِقِ","translation":"opposes","occurences":["4:115"]},{"word":"ٱلرَّسُولَ","translation":"the Messenger","occurences":["4:115"]},{"word":"مِنۢ","translation":"from","occurences":["4:115","4:128"]},{"word":"بَعْدِ","translation":"after","occurences":["4:115"]},{"word":"مَا","translation":"what","occurences":["4:115","4:115","4:116","4:126","4:127","4:131","4:131","4:132"]},{"word":"تَبَيَّنَ","translation":"(has) become clear","occurences":["4:115"]},{"word":"لَهُ","translation":"to him","occurences":["4:115"]},{"word":"ٱلْهُدَىٰ","translation":"(of) the guidance","occurences":["4:115"]},{"word":"وَيَتَّبِعْ","translation":"and he follows","occurences":["4:115"]},{"word":"غَيْرَ","translation":"other than","occurences":["4:115"]},{"word":"سَبِيلِ","translation":"(the) way","occurences":["4:115"]},{"word":"ٱلْمُؤْمِنِينَ","translation":"(of) the believers","occurences":["4:115","4:141","4:146"]},{"word":"نُوَلِّهِۦ","translation":"We will turn him","occurences":["4:115"]},{"word":"تَوَلَّىٰ","translation":"he (has) turned","occurences":["4:115"]},{"word":"وَنُصْلِهِۦ","translation":"and We will burn him","occurences":["4:115"]},{"word":"جَهَنَّمَ ۖ","translation":"(in) Hell","occurences":["4:115"]},{"word":"وَسَآءَتْ","translation":"and evil it is","occurences":["4:115"]},{"word":"مَصِيرًا","translation":"(as) a destination","occurences":["4:115"]},{"word":"إِنَّ","translation":"Indeed","occurences":["4:116","4:137","4:140","4:142","4:145"]},{"word":"ٱللَّهَ","translation":"Allah","occurences":["4:116","4:127","4:128","4:129","4:135","4:140","4:142","4:142"]},{"word":"لَا","translation":"does not","occurences":["4:116","4:127","4:144"]},{"word":"يَغْفِرُ","translation":"forgive","occurences":["4:116"]},{"word":"أَن","translation":"that","occurences":["4:116","4:127","4:128","4:129","4:135","4:144"]},{"word":"يُشْرَكَ","translation":"partners be associated","occurences":["4:116"]},{"word":"بِهِۦ","translation":"with Him","occurences":["4:116","4:123","4:127"]},{"word":"وَيَغْفِرُ","translation":"but He forgives","occurences":["4:116"]},{"word":"دُونَ","translation":"other than","occurences":["4:116"]},{"word":"لِمَن","translation":"for whom","occurences":["4:116"]},{"word":"يَشَآءُ ۚ","translation":"He wills","occurences":["4:116"]},{"word":"يُشْرِكْ","translation":"associates partners","occurences":["4:116"]},{"word":"بِٱللَّهِ","translation":"with Allah","occurences":["4:116","4:132","4:136","4:136","4:146"]},{"word":"فَقَدْ","translation":"then surely","occurences":["4:116","4:119","4:136"]},{"word":"ضَلَّ","translation":"he lost (the) way","occurences":["4:116","4:136"]},{"word":"ضَلَـٰلًۢا","translation":"straying","occurences":["4:116","4:136"]},{"word":"بَعِيدًا","translation":"far away","occurences":["4:116","4:136"]},{"word":"إِن","translation":"Not","occurences":["4:117","4:133","4:135","4:147"]},{"word":"يَدْعُونَ","translation":"they invoke","occurences":["4:117","4:117"]},{"word":"مِن","translation":"from","occurences":["4:117","4:122","4:123","4:124","4:131","4:136","4:139","4:144"]},{"word":"دُونِهِۦٓ","translation":"besides Him","occurences":["4:117"]},{"word":"إِلَّآ","translation":"but","occurences":["4:117"]},{"word":"إِنَـٰثًۭا","translation":"female (deities)","occurences":["4:117"]},{"word":"وَإِن","translation":"and not","occurences":["4:117","4:128","4:129","4:130","4:131","4:135","4:141"]},{"word":"شَيْطَـٰنًۭا","translation":"Shaitaan ","occurences":["4:117"]},{"word":"مَّرِيدًۭا","translation":"rebellious","occurences":["4:117"]},{"word":"لَّعَنَهُ","translation":"He was cursed","occurences":["4:118"]},{"word":"ٱللَّهُ ۘ","translation":"by Allah","occurences":["4:118"]},{"word":"وَقَالَ","translation":"and he said","occurences":["4:118"]},{"word":"لَأَتَّخِذَنَّ","translation":"I will surely take","occurences":["4:118"]},{"word":"مِنْ","translation":"from","occurences":["4:118","4:127"]},{"word":"عِبَادِكَ","translation":"your slaves","occurences":["4:118"]},{"word":"نَصِيبًۭا","translation":"a portion","occurences":["4:118"]},{"word":"مَّفْرُوضًۭا","translation":"appointed","occurences":["4:118"]},{"word":"وَلَأُضِلَّنَّهُمْ","translation":"And I will surely mislead them","occurences":["4:119"]},{"word":"وَلَأُمَنِّيَنَّهُمْ","translation":"and surely arouse desires in them","occurences":["4:119"]},{"word":"وَلَـَٔامُرَنَّهُمْ","translation":"and surely I will order them","occurences":["4:119","4:119"]},{"word":"فَلَيُبَتِّكُنَّ","translation":"so they will surely cut off","occurences":["4:119"]},{"word":"ءَاذَانَ","translation":"(the) ears","occurences":["4:119"]},{"word":"ٱلْأَنْعَـٰمِ","translation":"(of) the cattle","occurences":["4:119"]},{"word":"فَلَيُغَيِّرُنَّ","translation":"so they will surely change","occurences":["4:119"]},{"word":"خَلْقَ","translation":"(the) creation","occurences":["4:119"]},{"word":"ٱللَّهِ ۚ","translation":"(of) Allah","occurences":["4:119"]},{"word":"يَتَّخِذِ","translation":"takes","occurences":["4:119"]},{"word":"ٱلشَّيْطَـٰنَ","translation":"the Shaitaan","occurences":["4:119"]},{"word":"وَلِيًّۭا","translation":"(as) a friend","occurences":["4:119","4:123"]},{"word":"دُونِ","translation":"besides","occurences":["4:119","4:123","4:139","4:144"]},{"word":"خَسِرَ","translation":"he (has) lost ","occurences":["4:119"]},{"word":"خُسْرَانًۭا","translation":"a loss","occurences":["4:119"]},{"word":"مُّبِينًۭا","translation":"manifest","occurences":["4:119"]},{"word":"يَعِدُهُمْ","translation":"He promises them","occurences":["4:120"]},{"word":"وَيُمَنِّيهِمْ ۖ","translation":"and arouses desires in them","occurences":["4:120"]},{"word":"وَمَا","translation":"and not","occurences":["4:120","4:126","4:127","4:127","4:131","4:131","4:132"]},{"word":"يَعِدُهُمُ","translation":"promises them","occurences":["4:120"]},{"word":"ٱلشَّيْطَـٰنُ","translation":"the Shaitaan ","occurences":["4:120"]},{"word":"غُرُورًا","translation":"deception","occurences":["4:120"]},{"word":"أُو۟لَـٰٓئِكَ","translation":"Those ","occurences":["4:121"]},{"word":"مَأْوَىٰهُمْ","translation":"their abode","occurences":["4:121"]},{"word":"جَهَنَّمُ","translation":"(is) Hell","occurences":["4:121"]},{"word":"وَلَا","translation":"and not","occurences":["4:121","4:123","4:123","4:124","4:137","4:142"]},{"word":"يَجِدُونَ","translation":"they will find","occurences":["4:121"]},{"word":"عَنْهَا","translation":"from it","occurences":["4:121"]},{"word":"مَحِيصًۭا","translation":"any escape","occurences":["4:121"]},{"word":"وَٱلَّذِينَ","translation":"And those who","occurences":["4:122"]},{"word":"ءَامَنُوا۟","translation":"believe[d]","occurences":["4:122","4:135","4:137","4:137","4:144"]},{"word":"وَعَمِلُوا۟","translation":"and do","occurences":["4:122"]},{"word":"ٱلصَّـٰلِحَـٰتِ","translation":"[the] righteous deeds","occurences":["4:122","4:124"]},{"word":"سَنُدْخِلُهُمْ","translation":"We will admit them","occurences":["4:122"]},{"word":"جَنَّـٰتٍۢ","translation":"(in) Gardens","occurences":["4:122"]},{"word":"تَجْرِى","translation":"flow","occurences":["4:122"]},{"word":"تَحْتِهَا","translation":"underneath it","occurences":["4:122"]},{"word":"ٱلْأَنْهَـٰرُ","translation":"the rivers","occurences":["4:122"]},{"word":"خَـٰلِدِينَ","translation":"will abide","occurences":["4:122"]},{"word":"فِيهَآ","translation":"in it","occurences":["4:122"]},{"word":"أَبَدًۭا ۖ","translation":"forever","occurences":["4:122"]},{"word":"وَعْدَ","translation":"A Promise","occurences":["4:122"]},{"word":"حَقًّۭا ۚ","translation":"(in) truth","occurences":["4:122"]},{"word":"وَمَنْ","translation":"and who","occurences":["4:122","4:125"]},{"word":"أَصْدَقُ","translation":"(is) truer","occurences":["4:122"]},{"word":"مِنَ","translation":"than","occurences":["4:122","4:124","4:127","4:145"]},{"word":"قِيلًۭا","translation":"(in) statement","occurences":["4:122"]},{"word":"لَّيْسَ","translation":"Not","occurences":["4:123"]},{"word":"بِأَمَانِيِّكُمْ","translation":"by your desire","occurences":["4:123"]},{"word":"وَلَآ","translation":"and not","occurences":["4:123","4:143"]},{"word":"أَمَانِىِّ","translation":"(by the) desire","occurences":["4:123"]},{"word":"أَهْلِ","translation":"(of the) People","occurences":["4:123"]},{"word":"ٱلْكِتَـٰبِ ۗ","translation":"(of) the Book","occurences":["4:123"]},{"word":"مَن","translation":"Whoever","occurences":["4:123"]},{"word":"يَعْمَلْ","translation":"does","occurences":["4:123","4:124"]},{"word":"سُوٓءًۭا","translation":"evil","occurences":["4:123"]},{"word":"يُجْزَ","translation":"will be recompensed","occurences":["4:123"]},{"word":"يَجِدْ","translation":"he will find","occurences":["4:123"]},{"word":"لَهُۥ","translation":"for him","occurences":["4:123","4:143"]},{"word":"نَصِيرًۭا","translation":"any helper","occurences":["4:123"]},{"word":"ذَكَرٍ","translation":"(the) male","occurences":["4:124"]},{"word":"أُنثَىٰ","translation":"female","occurences":["4:124"]},{"word":"وَهُوَ","translation":"and he","occurences":["4:124","4:125","4:142"]},{"word":"مُؤْمِنٌۭ","translation":"(is) a believer","occurences":["4:124"]},{"word":"فَأُو۟لَـٰٓئِكَ","translation":"then those","occurences":["4:124","4:146"]},{"word":"يَدْخُلُونَ","translation":"will enter","occurences":["4:124"]},{"word":"ٱلْجَنَّةَ","translation":"Paradise","occurences":["4:124"]},{"word":"يُظْلَمُونَ","translation":"they will be wronged","occurences":["4:124"]},{"word":"نَقِيرًۭا","translation":"(even as much as) the speck on a date-seed","occurences":["4:124"]},{"word":"أَحْسَنُ","translation":"(is) better","occurences":["4:125"]},{"word":"دِينًۭا","translation":"(in) religion","occurences":["4:125"]},{"word":"مِّمَّنْ","translation":"than (one) who","occurences":["4:125"]},{"word":"أَسْلَمَ","translation":"submits","occurences":["4:125"]},{"word":"وَجْهَهُۥ","translation":"his face","occurences":["4:125"]},{"word":"لِلَّهِ","translation":"to Allah","occurences":["4:125","4:131","4:135","4:139","4:144","4:146"]},{"word":"مُحْسِنٌۭ","translation":"(is) a good-doer","occurences":["4:125"]},{"word":"وَٱتَّبَعَ","translation":"and follows","occurences":["4:125"]},{"word":"مِلَّةَ","translation":"(the) religion","occurences":["4:125"]},{"word":"إِبْرَٰهِيمَ","translation":"(of) Ibrahim","occurences":["4:125","4:125"]},{"word":"حَنِيفًۭا ۗ","translation":"(the) upright","occurences":["4:125"]},{"word":"وَٱتَّخَذَ","translation":"And was taken","occurences":["4:125"]},{"word":"ٱللَّهُ","translation":"(by) Allah","occurences":["4:125","4:126","4:127","4:130","4:130","4:131","4:133","4:134","4:137","4:141","4:143","4:146","4:147","4:147"]},{"word":"خَلِيلًۭا","translation":"(as) a friend","occurences":["4:125"]},{"word":"وَلِلَّهِ","translation":"And for Allah","occurences":["4:126","4:131","4:132"]},{"word":"ٱلسَّمَـٰوَٰتِ","translation":"the heavens","occurences":["4:126","4:131","4:131","4:132"]},{"word":"ٱلْأَرْضِ ۚ","translation":"the earth","occurences":["4:126","4:131","4:132"]},{"word":"وَكَانَ","translation":"and is","occurences":["4:126","4:130","4:131","4:133","4:134","4:147"]},{"word":"بِكُلِّ","translation":"of every","occurences":["4:126"]},{"word":"شَىْءٍۢ","translation":"thing","occurences":["4:126"]},{"word":"مُّحِيطًۭا","translation":"All-Encompassing","occurences":["4:126"]},{"word":"وَيَسْتَفْتُونَكَ","translation":"And they seek your ruling","occurences":["4:127"]},{"word":"ٱلنِّسَآءِ ۖ","translation":"the women","occurences":["4:127"]},{"word":"قُلِ","translation":"Say","occurences":["4:127"]},{"word":"يُفْتِيكُمْ","translation":"gives you the ruling","occurences":["4:127"]},{"word":"فِيهِنَّ","translation":"about them","occurences":["4:127"]},{"word":"يُتْلَىٰ","translation":"is recited","occurences":["4:127"]},{"word":"عَلَيْكُمْ","translation":"to you","occurences":["4:127","4:140","4:141","4:144"]},{"word":"ٱلْكِتَـٰبِ","translation":"the Book","occurences":["4:127","4:140"]},{"word":"يَتَـٰمَى","translation":"orphans","occurences":["4:127"]},{"word":"ٱلنِّسَآءِ","translation":"(of) girls","occurences":["4:127","4:129"]},{"word":"ٱلَّـٰتِى","translation":"(to) whom","occurences":["4:127"]},{"word":"تُؤْتُونَهُنَّ","translation":"(do) you give them","occurences":["4:127"]},{"word":"كُتِبَ","translation":"is ordained","occurences":["4:127"]},{"word":"لَهُنَّ","translation":"for them","occurences":["4:127"]},{"word":"وَتَرْغَبُونَ","translation":"and you desire","occurences":["4:127"]},{"word":"تَنكِحُوهُنَّ","translation":"marry them","occurences":["4:127"]},{"word":"وَٱلْمُسْتَضْعَفِينَ","translation":"and the ones who are weak","occurences":["4:127"]},{"word":"ٱلْوِلْدَٰنِ","translation":"the children","occurences":["4:127"]},{"word":"وَأَن","translation":"and to","occurences":["4:127"]},{"word":"تَقُومُوا۟","translation":"stand","occurences":["4:127"]},{"word":"لِلْيَتَـٰمَىٰ","translation":"for orphans","occurences":["4:127"]},{"word":"بِٱلْقِسْطِ ۚ","translation":"with justice","occurences":["4:127"]},{"word":"تَفْعَلُوا۟","translation":"you do","occurences":["4:127"]},{"word":"خَيْرٍۢ","translation":"good","occurences":["4:127"]},{"word":"فَإِنَّ","translation":"then indeed","occurences":["4:127","4:128","4:129","4:131","4:135","4:139"]},{"word":"كَانَ","translation":"is","occurences":["4:127","4:128","4:129","4:134","4:135","4:141","4:141"]},{"word":"عَلِيمًۭا","translation":"All-Knowing","occurences":["4:127","4:147"]},{"word":"وَإِنِ","translation":"And if","occurences":["4:128"]},{"word":"ٱمْرَأَةٌ","translation":"a woman","occurences":["4:128"]},{"word":"خَافَتْ","translation":"fears","occurences":["4:128"]},{"word":"بَعْلِهَا","translation":"her husband","occurences":["4:128"]},{"word":"نُشُوزًا","translation":"ill-conduct","occurences":["4:128"]},{"word":"إِعْرَاضًۭا","translation":"desertion","occurences":["4:128"]},{"word":"فَلَا","translation":"then (there is) no","occurences":["4:128","4:129","4:135","4:140"]},{"word":"جُنَاحَ","translation":"sin","occurences":["4:128"]},{"word":"عَلَيْهِمَآ","translation":"on both of them","occurences":["4:128"]},{"word":"يُصْلِحَا","translation":"they make terms of peace","occurences":["4:128"]},{"word":"بَيْنَهُمَا","translation":"between themselves ","occurences":["4:128"]},{"word":"صُلْحًۭا ۚ","translation":"a reconciliation","occurences":["4:128"]},{"word":"وَٱلصُّلْحُ","translation":"and [the] reconciliation","occurences":["4:128"]},{"word":"خَيْرٌۭ ۗ","translation":"(is) best","occurences":["4:128"]},{"word":"وَأُحْضِرَتِ","translation":"And are swayed","occurences":["4:128"]},{"word":"ٱلْأَنفُسُ","translation":"the souls","occurences":["4:128"]},{"word":"ٱلشُّحَّ ۚ","translation":"(by) greed","occurences":["4:128"]},{"word":"تُحْسِنُوا۟","translation":"you do good","occurences":["4:128"]},{"word":"وَتَتَّقُوا۟","translation":"and fear (Allah)","occurences":["4:128","4:129"]},{"word":"بِمَا","translation":"of what","occurences":["4:128","4:135"]},{"word":"تَعْمَلُونَ","translation":"you do","occurences":["4:128","4:135"]},{"word":"خَبِيرًۭا","translation":"All-Aware","occurences":["4:128","4:135"]},{"word":"وَلَن","translation":"And never","occurences":["4:129","4:141","4:145"]},{"word":"تَسْتَطِيعُوٓا۟","translation":"will you be able","occurences":["4:129"]},{"word":"تَعْدِلُوا۟","translation":"deal justly","occurences":["4:129"]},{"word":"وَلَوْ","translation":"even if","occurences":["4:129","4:135"]},{"word":"حَرَصْتُمْ ۖ","translation":"you desired","occurences":["4:129"]},{"word":"تَمِيلُوا۟","translation":"incline","occurences":["4:129"]},{"word":"كُلَّ","translation":"(with) all","occurences":["4:129"]},{"word":"ٱلْمَيْلِ","translation":"the inclination","occurences":["4:129"]},{"word":"فَتَذَرُوهَا","translation":"and leave her (the other)","occurences":["4:129"]},{"word":"كَٱلْمُعَلَّقَةِ ۚ","translation":"like the suspended one","occurences":["4:129"]},{"word":"تُصْلِحُوا۟","translation":"you reconcile","occurences":["4:129"]},{"word":"غَفُورًۭا","translation":"Oft-Forgiving","occurences":["4:129"]},{"word":"رَّحِيمًۭا","translation":"Most Merciful","occurences":["4:129"]},{"word":"يَتَفَرَّقَا","translation":"they separate","occurences":["4:130"]},{"word":"يُغْنِ","translation":"will be enriched","occurences":["4:130"]},{"word":"كُلًّۭا","translation":"each (of them)","occurences":["4:130"]},{"word":"سَعَتِهِۦ ۚ","translation":"His abundance","occurences":["4:130"]},{"word":"وَٰسِعًا","translation":"All-Encompassing","occurences":["4:130"]},{"word":"حَكِيمًۭا","translation":"All-Wise","occurences":["4:130"]},{"word":"ٱلْأَرْضِ ۗ","translation":"the earth","occurences":["4:131"]},{"word":"وَلَقَدْ","translation":"And surely","occurences":["4:131"]},{"word":"وَصَّيْنَا","translation":"We have instructed","occurences":["4:131"]},{"word":"ٱلَّذِينَ","translation":"those who","occurences":["4:131","4:135","4:136","4:137","4:139","4:141","4:144","4:146"]},{"word":"أُوتُوا۟","translation":"were given","occurences":["4:131"]},{"word":"ٱلْكِتَـٰبَ","translation":"the Book","occurences":["4:131"]},{"word":"قَبْلِكُمْ","translation":"before you","occurences":["4:131"]},{"word":"وَإِيَّاكُمْ","translation":"and yourselves","occurences":["4:131"]},{"word":"أَنِ","translation":"that","occurences":["4:131"]},{"word":"ٱتَّقُوا۟","translation":"you fear","occurences":["4:131"]},{"word":"ٱللَّهَ ۚ","translation":"Allah","occurences":["4:131"]},{"word":"تَكْفُرُوا۟","translation":"you disbelieve ","occurences":["4:131"]},{"word":"غَنِيًّا","translation":"Free of need","occurences":["4:131","4:135"]},{"word":"حَمِيدًۭا","translation":"Praiseworthy","occurences":["4:131"]},{"word":"وَكَفَىٰ","translation":"And is sufficient","occurences":["4:132"]},{"word":"وَكِيلًا","translation":"(as) a Disposer of affairs","occurences":["4:132"]},{"word":"يَشَأْ","translation":"He wills","occurences":["4:133"]},{"word":"يُذْهِبْكُمْ","translation":"He can take you away","occurences":["4:133"]},{"word":"أَيُّهَا","translation":"O","occurences":["4:133"]},{"word":"ٱلنَّاسُ","translation":"people","occurences":["4:133"]},{"word":"وَيَأْتِ","translation":"and bring","occurences":["4:133"]},{"word":"بِـَٔاخَرِينَ ۚ","translation":"others","occurences":["4:133"]},{"word":"عَلَىٰ","translation":"over","occurences":["4:133","4:136"]},{"word":"قَدِيرًۭا","translation":"All-Powerful","occurences":["4:133"]},{"word":"مَّن","translation":"Whoever","occurences":["4:134"]},{"word":"يُرِيدُ","translation":"desires","occurences":["4:134"]},{"word":"ثَوَابَ","translation":"reward","occurences":["4:134"]},{"word":"ٱلدُّنْيَا","translation":"(of) the world ","occurences":["4:134","4:134"]},{"word":"فَعِندَ","translation":"then with","occurences":["4:134"]},{"word":"ثَوَابُ","translation":"(is the) reward","occurences":["4:134"]},{"word":"وَٱلْـَٔاخِرَةِ ۚ","translation":"and the Hereafter","occurences":["4:134"]},{"word":"سَمِيعًۢا","translation":"All-Hearing","occurences":["4:134"]},{"word":"بَصِيرًۭا","translation":"All-Seeing","occurences":["4:134"]},{"word":"۞ يَـٰٓأَيُّهَا","translation":"O you","occurences":["4:135"]},{"word":"كُونُوا۟","translation":"Be","occurences":["4:135"]},{"word":"قَوَّٰمِينَ","translation":"custodians","occurences":["4:135"]},{"word":"بِٱلْقِسْطِ","translation":"of justice","occurences":["4:135"]},{"word":"شُهَدَآءَ","translation":"(as) witnesses","occurences":["4:135"]},{"word":"عَلَىٰٓ","translation":"(it is) against","occurences":["4:135"]},{"word":"أَنفُسِكُمْ","translation":"yourselves","occurences":["4:135"]},{"word":"أَوِ","translation":"or","occurences":["4:135"]},{"word":"ٱلْوَٰلِدَيْنِ","translation":"the parents","occurences":["4:135"]},{"word":"وَٱلْأَقْرَبِينَ ۚ","translation":"and the relatives","occurences":["4:135"]},{"word":"يَكُنْ","translation":"he be","occurences":["4:135"]},{"word":"فَقِيرًۭا","translation":"poor","occurences":["4:135"]},{"word":"فَٱللَّهُ","translation":"for Allah","occurences":["4:135","4:141"]},{"word":"أَوْلَىٰ","translation":"(is) nearer","occurences":["4:135"]},{"word":"بِهِمَا ۖ","translation":"to both of them","occurences":["4:135"]},{"word":"تَتَّبِعُوا۟","translation":"follow","occurences":["4:135"]},{"word":"ٱلْهَوَىٰٓ","translation":"the desire","occurences":["4:135"]},{"word":"تَعْدِلُوا۟ ۚ","translation":"you deviate","occurences":["4:135"]},{"word":"تَلْوُۥٓا۟","translation":"you distort","occurences":["4:135"]},{"word":"تُعْرِضُوا۟","translation":"refrain","occurences":["4:135"]},{"word":"يَـٰٓأَيُّهَا","translation":"O you","occurences":["4:136","4:144"]},{"word":"ءَامَنُوٓا۟","translation":"believe[d]","occurences":["4:136"]},{"word":"ءَامِنُوا۟","translation":"Believe","occurences":["4:136"]},{"word":"وَرَسُولِهِۦ","translation":"and His Messenger","occurences":["4:136"]},{"word":"وَٱلْكِتَـٰبِ","translation":"and the Book","occurences":["4:136","4:136"]},{"word":"ٱلَّذِى","translation":"which","occurences":["4:136"]},{"word":"نَزَّلَ","translation":"He revealed","occurences":["4:136","4:140"]},{"word":"رَسُولِهِۦ","translation":"His Messenger","occurences":["4:136"]},{"word":"ٱلَّذِىٓ","translation":"which","occurences":["4:136"]},{"word":"أَنزَلَ","translation":"He revealed","occurences":["4:136"]},{"word":"قَبْلُ ۚ","translation":"before","occurences":["4:136"]},{"word":"يَكْفُرْ","translation":"disbelieves","occurences":["4:136"]},{"word":"وَمَلَـٰٓئِكَتِهِۦ","translation":"and His Angels","occurences":["4:136"]},{"word":"وَكُتُبِهِۦ","translation":"and His Books","occurences":["4:136"]},{"word":"وَرُسُلِهِۦ","translation":"and His Messengers","occurences":["4:136"]},{"word":"وَٱلْيَوْمِ","translation":"and the Day","occurences":["4:136"]},{"word":"ٱلْـَٔاخِرِ","translation":"the Last","occurences":["4:136"]},{"word":"ثُمَّ","translation":"then","occurences":["4:137","4:137","4:137","4:137"]},{"word":"كَفَرُوا۟","translation":"disbelieved","occurences":["4:137","4:137"]},{"word":"ٱزْدَادُوا۟","translation":"increased","occurences":["4:137"]},{"word":"كُفْرًۭا","translation":"(in) disbelief ","occurences":["4:137"]},{"word":"لَّمْ","translation":"not","occurences":["4:137"]},{"word":"يَكُنِ","translation":"will","occurences":["4:137"]},{"word":"لِيَغْفِرَ","translation":"forgive","occurences":["4:137"]},{"word":"لَهُمْ","translation":"[for] them","occurences":["4:137","4:138","4:145"]},{"word":"لِيَهْدِيَهُمْ","translation":"will guide them","occurences":["4:137"]},{"word":"سَبِيلًۢا","translation":"(to) a (right) way","occurences":["4:137"]},{"word":"بَشِّرِ","translation":"Give tidings","occurences":["4:138"]},{"word":"ٱلْمُنَـٰفِقِينَ","translation":"(to) the hypocrites","occurences":["4:138","4:140","4:142","4:145"]},{"word":"بِأَنَّ","translation":"that","occurences":["4:138"]},{"word":"عَذَابًا","translation":"(is) a punishment","occurences":["4:138"]},{"word":"أَلِيمًا","translation":"painful ","occurences":["4:138"]},{"word":"يَتَّخِذُونَ","translation":"take","occurences":["4:139"]},{"word":"ٱلْكَـٰفِرِينَ","translation":"the disbelievers","occurences":["4:139","4:144"]},{"word":"أَوْلِيَآءَ","translation":"(as) allies","occurences":["4:139","4:144"]},{"word":"ٱلْمُؤْمِنِينَ ۚ","translation":"the believers","occurences":["4:139","4:141","4:144"]},{"word":"أَيَبْتَغُونَ","translation":"Do they seek","occurences":["4:139"]},{"word":"عِندَهُمُ","translation":"with them","occurences":["4:139"]},{"word":"ٱلْعِزَّةَ","translation":"the honor","occurences":["4:139","4:139"]},{"word":"جَمِيعًۭا","translation":"all","occurences":["4:139"]},{"word":"وَقَدْ","translation":"And surely","occurences":["4:140"]},{"word":"أَنْ","translation":"that","occurences":["4:140"]},{"word":"إِذَا","translation":"when","occurences":["4:140"]},{"word":"سَمِعْتُمْ","translation":"you hear","occurences":["4:140"]},{"word":"ءَايَـٰتِ","translation":"(the) Verses","occurences":["4:140"]},{"word":"يُكْفَرُ","translation":"being rejected","occurences":["4:140"]},{"word":"بِهَا","translation":"[it]","occurences":["4:140","4:140"]},{"word":"وَيُسْتَهْزَأُ","translation":"and ridiculed","occurences":["4:140"]},{"word":"تَقْعُدُوا۟","translation":"sit","occurences":["4:140"]},{"word":"مَعَهُمْ","translation":"with them","occurences":["4:140"]},{"word":"حَتَّىٰ","translation":"until","occurences":["4:140"]},{"word":"يَخُوضُوا۟","translation":"they engage","occurences":["4:140"]},{"word":"حَدِيثٍ","translation":"a conversation","occurences":["4:140"]},{"word":"غَيْرِهِۦٓ ۚ","translation":"other than that","occurences":["4:140"]},{"word":"إِنَّكُمْ","translation":"Indeed, you","occurences":["4:140"]},{"word":"إِذًۭا","translation":"then","occurences":["4:140"]},{"word":"مِّثْلُهُمْ ۗ","translation":"(would be) like them","occurences":["4:140"]},{"word":"جَامِعُ","translation":"will gather","occurences":["4:140"]},{"word":"وَٱلْكَـٰفِرِينَ","translation":"and the disbelievers","occurences":["4:140"]},{"word":"جَهَنَّمَ","translation":"Hell","occurences":["4:140"]},{"word":"جَمِيعًا","translation":"all together","occurences":["4:140"]},{"word":"يَتَرَبَّصُونَ","translation":"are waiting","occurences":["4:141"]},{"word":"بِكُمْ","translation":"for you","occurences":["4:141"]},{"word":"فَإِن","translation":"Then if","occurences":["4:141"]},{"word":"لَكُمْ","translation":"for you","occurences":["4:141"]},{"word":"فَتْحٌۭ","translation":"a victory","occurences":["4:141"]},{"word":"مِّنَ","translation":"from","occurences":["4:141","4:141"]},{"word":"قَالُوٓا۟","translation":"they say","occurences":["4:141","4:141"]},{"word":"أَلَمْ","translation":"Were not","occurences":["4:141","4:141"]},{"word":"نَكُن","translation":"we","occurences":["4:141"]},{"word":"مَّعَكُمْ","translation":"with you","occurences":["4:141"]},{"word":"لِلْكَـٰفِرِينَ","translation":"for the disbelievers","occurences":["4:141","4:141"]},{"word":"نَصِيبٌۭ","translation":"a chance","occurences":["4:141"]},{"word":"نَسْتَحْوِذْ","translation":"we have advantage","occurences":["4:141"]},{"word":"وَنَمْنَعْكُم","translation":"and we protected you","occurences":["4:141"]},{"word":"يَحْكُمُ","translation":"will judge","occurences":["4:141"]},{"word":"بَيْنَكُمْ","translation":"between you","occurences":["4:141"]},{"word":"يَوْمَ","translation":"(on the) Day","occurences":["4:141"]},{"word":"ٱلْقِيَـٰمَةِ ۗ","translation":"(of) the Resurrection","occurences":["4:141"]},{"word":"يَجْعَلَ","translation":"will make","occurences":["4:141"]},{"word":"عَلَى","translation":"over","occurences":["4:141"]},{"word":"سَبِيلًا","translation":"a way","occurences":["4:141"]},{"word":"يُخَـٰدِعُونَ","translation":"(seek to) deceive","occurences":["4:142"]},{"word":"خَـٰدِعُهُمْ","translation":"who deceives them","occurences":["4:142"]},{"word":"وَإِذَا","translation":"And when","occurences":["4:142"]},{"word":"قَامُوٓا۟","translation":"they stand","occurences":["4:142"]},{"word":"إِلَى","translation":"for","occurences":["4:142"]},{"word":"ٱلصَّلَوٰةِ","translation":"the prayer","occurences":["4:142"]},{"word":"قَامُوا۟","translation":"they stand","occurences":["4:142"]},{"word":"كُسَالَىٰ","translation":"lazily","occurences":["4:142"]},{"word":"يُرَآءُونَ","translation":"showing off","occurences":["4:142"]},{"word":"ٱلنَّاسَ","translation":"(to) the people","occurences":["4:142"]},{"word":"يَذْكُرُونَ","translation":"they remember","occurences":["4:142"]},{"word":"قَلِيلًۭا","translation":"a little","occurences":["4:142"]},{"word":"مُّذَبْذَبِينَ","translation":"Wavering","occurences":["4:143"]},{"word":"لَآ","translation":"not","occurences":["4:143"]},{"word":"إِلَىٰ","translation":"to","occurences":["4:143","4:143"]},{"word":"هَـٰٓؤُلَآءِ","translation":"these","occurences":["4:143"]},{"word":"هَـٰٓؤُلَآءِ ۚ","translation":"those","occurences":["4:143"]},{"word":"يُضْلِلِ","translation":"has been lead astray","occurences":["4:143"]},{"word":"فَلَن","translation":"then never","occurences":["4:143"]},{"word":"تَجِدَ","translation":"you will find","occurences":["4:143","4:145"]},{"word":"سَبِيلًۭا","translation":"a way","occurences":["4:143"]},{"word":"تَتَّخِذُوا۟","translation":"take","occurences":["4:144"]},{"word":"أَتُرِيدُونَ","translation":"Do you wish","occurences":["4:144"]},{"word":"تَجْعَلُوا۟","translation":"you make","occurences":["4:144"]},{"word":"سُلْطَـٰنًۭا","translation":"an evidence","occurences":["4:144"]},{"word":"مُّبِينًا","translation":"clear","occurences":["4:144"]},{"word":"ٱلدَّرْكِ","translation":"the depths","occurences":["4:145"]},{"word":"ٱلْأَسْفَلِ","translation":"the lowest","occurences":["4:145"]},{"word":"ٱلنَّارِ","translation":"the Fire","occurences":["4:145"]},{"word":"نَصِيرًا","translation":"any helper","occurences":["4:145"]},{"word":"تَابُوا۟","translation":"repent","occurences":["4:146"]},{"word":"وَأَصْلَحُوا۟","translation":"and correct (themselves)","occurences":["4:146"]},{"word":"وَٱعْتَصَمُوا۟","translation":"and hold fast","occurences":["4:146"]},{"word":"وَأَخْلَصُوا۟","translation":"and are sincere","occurences":["4:146"]},{"word":"دِينَهُمْ","translation":"(in) their religion","occurences":["4:146"]},{"word":"مَعَ","translation":"with","occurences":["4:146"]},{"word":"ٱلْمُؤْمِنِينَ ۖ","translation":"the believers","occurences":["4:146"]},{"word":"وَسَوْفَ","translation":"And soon","occurences":["4:146"]},{"word":"يُؤْتِ","translation":"will be given","occurences":["4:146"]},{"word":"مَّا","translation":"What","occurences":["4:147"]},{"word":"يَفْعَلُ","translation":"would do","occurences":["4:147"]},{"word":"بِعَذَابِكُمْ","translation":"by punishing you","occurences":["4:147"]},{"word":"شَكَرْتُمْ","translation":"you are grateful","occurences":["4:147"]},{"word":"وَءَامَنتُمْ ۚ","translation":"and you believe","occurences":["4:147"]},{"word":"شَاكِرًا","translation":"All-Appreciative","occurences":["4:147"]}],"wordCount":415}