[{"word":"وَمَا","translation":"And not","occurences":["4:92"]},{"word":"كَانَ","translation":"is","occurences":["4:92","4:92","4:92","4:94"]},{"word":"لِمُؤْمِنٍ","translation":"for a believer","occurences":["4:92"]},{"word":"أَن","translation":"that","occurences":["4:92","4:92"]},{"word":"يَقْتُلَ","translation":"he kills","occurences":["4:92"]},{"word":"مُؤْمِنًا","translation":"a believer","occurences":["4:92","4:92"]},{"word":"إِلَّا","translation":"except","occurences":["4:92"]},{"word":"خَطَـًۭٔا ۚ","translation":"(by) mistake","occurences":["4:92"]},{"word":"وَمَن","translation":"And whoever","occurences":["4:92","4:93"]},{"word":"قَتَلَ","translation":"killed","occurences":["4:92"]},{"word":"خَطَـًۭٔا","translation":"(by) mistake","occurences":["4:92"]},{"word":"فَتَحْرِيرُ","translation":"then freeing","occurences":["4:92","4:92"]},{"word":"رَقَبَةٍۢ","translation":"(of) a slave","occurences":["4:92","4:92","4:92"]},{"word":"مُّؤْمِنَةٍۢ","translation":" believing","occurences":["4:92"]},{"word":"وَدِيَةٌۭ","translation":"and blood money","occurences":["4:92"]},{"word":"مُّسَلَّمَةٌ","translation":"(is to be) paid","occurences":["4:92","4:92"]},{"word":"إِلَىٰٓ","translation":"to","occurences":["4:92","4:92"]},{"word":"أَهْلِهِۦٓ","translation":"his family","occurences":["4:92"]},{"word":"إِلَّآ","translation":"unless","occurences":["4:92"]},{"word":"يَصَّدَّقُوا۟ ۚ","translation":"they remit (as) charity","occurences":["4:92"]},{"word":"فَإِن","translation":"But if","occurences":["4:92"]},{"word":"مِن","translation":"from","occurences":["4:92","4:92"]},{"word":"قَوْمٍ","translation":"a people","occurences":["4:92"]},{"word":"عَدُوٍّۢ","translation":"hostile","occurences":["4:92"]},{"word":"لَّكُمْ","translation":"to you","occurences":["4:92"]},{"word":"وَهُوَ","translation":"and he was","occurences":["4:92"]},{"word":"مُؤْمِنٌۭ","translation":"a believer","occurences":["4:92"]},{"word":"مُّؤْمِنَةٍۢ ۖ","translation":" believing","occurences":["4:92","4:92"]},{"word":"وَإِن","translation":"And if","occurences":["4:92"]},{"word":"قَوْمٍۭ","translation":"a people","occurences":["4:92"]},{"word":"بَيْنَكُمْ","translation":"between you","occurences":["4:92"]},{"word":"وَبَيْنَهُم","translation":"and between them","occurences":["4:92"]},{"word":"مِّيثَـٰقٌۭ","translation":"(is) a treaty","occurences":["4:92"]},{"word":"فَدِيَةٌۭ","translation":"then blood money","occurences":["4:92"]},{"word":"أَهْلِهِۦ","translation":"his family","occurences":["4:92"]},{"word":"وَتَحْرِيرُ","translation":"and freeing","occurences":["4:92"]},{"word":"فَمَن","translation":"And whoever","occurences":["4:92"]},{"word":"لَّمْ","translation":"(does) not","occurences":["4:92"]},{"word":"يَجِدْ","translation":"find","occurences":["4:92"]},{"word":"فَصِيَامُ","translation":"then fasting","occurences":["4:92"]},{"word":"شَهْرَيْنِ","translation":"(for) two months","occurences":["4:92"]},{"word":"مُتَتَابِعَيْنِ","translation":"consecutively","occurences":["4:92"]},{"word":"تَوْبَةًۭ","translation":"(seeking) repentance","occurences":["4:92"]},{"word":"مِّنَ","translation":"from","occurences":["4:92"]},{"word":"ٱللَّهِ ۗ","translation":"Allah","occurences":["4:92"]},{"word":"وَكَانَ","translation":"and is","occurences":["4:92"]},{"word":"ٱللَّهُ","translation":"Allah","occurences":["4:92","4:93","4:94"]},{"word":"عَلِيمًا","translation":"All-Knowing","occurences":["4:92"]},{"word":"حَكِيمًۭا","translation":"All-Wise","occurences":["4:92"]},{"word":"يَقْتُلْ","translation":"kills","occurences":["4:93"]},{"word":"مُؤْمِنًۭا","translation":"a believer","occurences":["4:93","4:94"]},{"word":"مُّتَعَمِّدًۭا","translation":"intentionally","occurences":["4:93"]},{"word":"فَجَزَآؤُهُۥ","translation":"then his recompense","occurences":["4:93"]},{"word":"جَهَنَّمُ","translation":"(is) Hell","occurences":["4:93"]},{"word":"خَـٰلِدًۭا","translation":"abiding forever","occurences":["4:93"]},{"word":"فِيهَا","translation":"in it","occurences":["4:93"]},{"word":"وَغَضِبَ","translation":"and will fall the wrath","occurences":["4:93"]},{"word":"عَلَيْهِ","translation":"on him","occurences":["4:93"]},{"word":"وَلَعَنَهُۥ","translation":"and He (will) curse him","occurences":["4:93"]},{"word":"وَأَعَدَّ","translation":"and He has prepared","occurences":["4:93"]},{"word":"لَهُۥ","translation":"for him","occurences":["4:93"]},{"word":"عَذَابًا","translation":"a punishment","occurences":["4:93"]},{"word":"عَظِيمًۭا","translation":"great","occurences":["4:93"]},{"word":"يَـٰٓأَيُّهَا","translation":"O you","occurences":["4:94"]},{"word":"ٱلَّذِينَ","translation":"who","occurences":["4:94"]},{"word":"ءَامَنُوٓا۟","translation":"believe[d]","occurences":["4:94"]},{"word":"إِذَا","translation":"When","occurences":["4:94"]},{"word":"ضَرَبْتُمْ","translation":"you go forth","occurences":["4:94"]},{"word":"فِى","translation":"in","occurences":["4:94"]},{"word":"سَبِيلِ","translation":"(the) way","occurences":["4:94"]},{"word":"ٱللَّهِ","translation":"(of) Allah","occurences":["4:94","4:94"]},{"word":"فَتَبَيَّنُوا۟","translation":"then investigate","occurences":["4:94"]},{"word":"وَلَا","translation":"and (do) not","occurences":["4:94"]},{"word":"تَقُولُوا۟","translation":"say","occurences":["4:94"]},{"word":"لِمَنْ","translation":"to (the one) who","occurences":["4:94"]},{"word":"أَلْقَىٰٓ","translation":"offers","occurences":["4:94"]},{"word":"إِلَيْكُمُ","translation":"to you","occurences":["4:94"]},{"word":"ٱلسَّلَـٰمَ","translation":"(a greeting of) peace","occurences":["4:94"]},{"word":"لَسْتَ","translation":"You are not","occurences":["4:94"]},{"word":"تَبْتَغُونَ","translation":"seeking","occurences":["4:94"]},{"word":"عَرَضَ","translation":"transitory gains","occurences":["4:94"]},{"word":"ٱلْحَيَوٰةِ","translation":"(of) the life","occurences":["4:94"]},{"word":"ٱلدُّنْيَا","translation":"(of) the world","occurences":["4:94"]},{"word":"فَعِندَ","translation":"for with","occurences":["4:94"]},{"word":"مَغَانِمُ","translation":"(are) booties","occurences":["4:94"]},{"word":"كَثِيرَةٌۭ ۚ","translation":"abundant","occurences":["4:94"]},{"word":"كَذَٰلِكَ","translation":"Like that","occurences":["4:94"]},{"word":"كُنتُم","translation":"you were","occurences":["4:94"]},{"word":"مِّن","translation":"from","occurences":["4:94"]},{"word":"قَبْلُ","translation":"before","occurences":["4:94"]},{"word":"فَمَنَّ","translation":"then conferred favor","occurences":["4:94"]},{"word":"عَلَيْكُمْ","translation":"upon you","occurences":["4:94"]},{"word":"فَتَبَيَّنُوٓا۟ ۚ","translation":"so investigate","occurences":["4:94"]},{"word":"إِنَّ","translation":"Indeed","occurences":["4:94"]},{"word":"ٱللَّهَ","translation":"Allah","occurences":["4:94"]},{"word":"بِمَا","translation":"of what","occurences":["4:94"]},{"word":"تَعْمَلُونَ","translation":"you do","occurences":["4:94"]},{"word":"خَبِيرًۭا","translation":"All-Aware","occurences":["4:94"]}]