[{"word":"وَمَا","translation":"And not","occurences":["12:104","12:106"]},{"word":"تَسْـَٔلُهُمْ","translation":"you ask them","occurences":["12:104"]},{"word":"عَلَيْهِ","translation":"for it","occurences":["12:104"]},{"word":"مِنْ","translation":"any","occurences":["12:104"]},{"word":"أَجْرٍ ۚ","translation":"reward","occurences":["12:104"]},{"word":"إِنْ","translation":"Not","occurences":["12:104"]},{"word":"هُوَ","translation":"(is) it","occurences":["12:104"]},{"word":"إِلَّا","translation":"but","occurences":["12:104","12:106","12:109"]},{"word":"ذِكْرٌۭ","translation":"a reminder","occurences":["12:104"]},{"word":"لِّلْعَـٰلَمِينَ","translation":"to the worlds","occurences":["12:104"]},{"word":"وَكَأَيِّن","translation":"And how many","occurences":["12:105"]},{"word":"مِّنْ","translation":"of","occurences":["12:105","12:107","12:109"]},{"word":"ءَايَةٍۢ","translation":"a Sign","occurences":["12:105"]},{"word":"فِى","translation":"in","occurences":["12:105","12:109","12:111"]},{"word":"ٱلسَّمَـٰوَٰتِ","translation":"the heavens","occurences":["12:105"]},{"word":"وَٱلْأَرْضِ","translation":"and the earth","occurences":["12:105"]},{"word":"يَمُرُّونَ","translation":"they pass","occurences":["12:105"]},{"word":"عَلَيْهَا","translation":"over it","occurences":["12:105"]},{"word":"وَهُمْ","translation":"while they","occurences":["12:105","12:107"]},{"word":"عَنْهَا","translation":"(are) from them","occurences":["12:105"]},{"word":"مُعْرِضُونَ","translation":"the ones who turn away","occurences":["12:105"]},{"word":"يُؤْمِنُ","translation":"believe","occurences":["12:106"]},{"word":"أَكْثَرُهُم","translation":"most of them","occurences":["12:106"]},{"word":"بِٱللَّهِ","translation":"in Allah","occurences":["12:106"]},{"word":"وَهُم","translation":"while they","occurences":["12:106"]},{"word":"مُّشْرِكُونَ","translation":"associate partners with Him","occurences":["12:106"]},{"word":"أَفَأَمِنُوٓا۟","translation":"Do they then feel secure","occurences":["12:107"]},{"word":"أَن","translation":"(against) that","occurences":["12:107"]},{"word":"تَأْتِيَهُمْ","translation":"comes to them","occurences":["12:107"]},{"word":"غَـٰشِيَةٌۭ","translation":"an overwhelming","occurences":["12:107"]},{"word":"عَذَابِ","translation":"punishment","occurences":["12:107"]},{"word":"ٱللَّهِ","translation":"(of) Allah","occurences":["12:107","12:108"]},{"word":"أَوْ","translation":"or","occurences":["12:107"]},{"word":"تَأْتِيَهُمُ","translation":"comes to them","occurences":["12:107"]},{"word":"ٱلسَّاعَةُ","translation":"the Hour","occurences":["12:107"]},{"word":"بَغْتَةًۭ","translation":"suddenly","occurences":["12:107"]},{"word":"لَا","translation":"(do) not","occurences":["12:107"]},{"word":"يَشْعُرُونَ","translation":"perceive","occurences":["12:107"]},{"word":"قُلْ","translation":"Say","occurences":["12:108"]},{"word":"هَـٰذِهِۦ","translation":"This","occurences":["12:108"]},{"word":"سَبِيلِىٓ","translation":"(is) my way","occurences":["12:108"]},{"word":"أَدْعُوٓا۟","translation":"I invite","occurences":["12:108"]},{"word":"إِلَى","translation":"to","occurences":["12:108"]},{"word":"ٱللَّهِ ۚ","translation":"Allah","occurences":["12:108"]},{"word":"عَلَىٰ","translation":"with","occurences":["12:108"]},{"word":"بَصِيرَةٍ","translation":"insight","occurences":["12:108"]},{"word":"أَنَا۠","translation":"I","occurences":["12:108","12:108"]},{"word":"وَمَنِ","translation":"and whoever","occurences":["12:108"]},{"word":"ٱتَّبَعَنِى ۖ","translation":"follows me","occurences":["12:108"]},{"word":"وَسُبْحَـٰنَ","translation":"And Glory be","occurences":["12:108"]},{"word":"وَمَآ","translation":"and not","occurences":["12:108","12:109"]},{"word":"مِنَ","translation":"of","occurences":["12:108"]},{"word":"ٱلْمُشْرِكِينَ","translation":"the polytheists","occurences":["12:108"]},{"word":"أَرْسَلْنَا","translation":"We sent","occurences":["12:109"]},{"word":"مِن","translation":"before you","occurences":["12:109","12:109"]},{"word":"قَبْلِكَ","translation":"before you","occurences":["12:109"]},{"word":"رِجَالًۭا","translation":"men","occurences":["12:109"]},{"word":"نُّوحِىٓ","translation":"We revealed","occurences":["12:109"]},{"word":"إِلَيْهِم","translation":"to them","occurences":["12:109"]},{"word":"أَهْلِ","translation":"(the) people","occurences":["12:109"]},{"word":"ٱلْقُرَىٰٓ ۗ","translation":"(of) the townships","occurences":["12:109"]},{"word":"أَفَلَمْ","translation":"So have not","occurences":["12:109"]},{"word":"يَسِيرُوا۟","translation":"they traveled","occurences":["12:109"]},{"word":"ٱلْأَرْضِ","translation":"the earth","occurences":["12:109"]},{"word":"فَيَنظُرُوا۟","translation":"and seen","occurences":["12:109"]},{"word":"كَيْفَ","translation":"how","occurences":["12:109"]},{"word":"كَانَ","translation":"was","occurences":["12:109","12:111","12:111"]},{"word":"عَـٰقِبَةُ","translation":"(the) end","occurences":["12:109"]},{"word":"ٱلَّذِينَ","translation":"(of) those who","occurences":["12:109"]},{"word":"قَبْلِهِمْ ۗ","translation":"(were) before them","occurences":["12:109"]},{"word":"وَلَدَارُ","translation":"And surely the home","occurences":["12:109"]},{"word":"ٱلْـَٔاخِرَةِ","translation":"(of) the Hereafter","occurences":["12:109"]},{"word":"خَيْرٌۭ","translation":"(is) best","occurences":["12:109"]},{"word":"لِّلَّذِينَ","translation":"for those who","occurences":["12:109"]},{"word":"ٱتَّقَوْا۟ ۗ","translation":"fear Allah","occurences":["12:109"]},{"word":"أَفَلَا","translation":"Then will not","occurences":["12:109"]},{"word":"تَعْقِلُونَ","translation":"you use reason","occurences":["12:109"]},{"word":"حَتَّىٰٓ","translation":"Until","occurences":["12:110"]},{"word":"إِذَا","translation":"when","occurences":["12:110"]},{"word":"ٱسْتَيْـَٔسَ","translation":"gave up hope","occurences":["12:110"]},{"word":"ٱلرُّسُلُ","translation":"the Messengers","occurences":["12:110"]},{"word":"وَظَنُّوٓا۟","translation":"and thought","occurences":["12:110"]},{"word":"أَنَّهُمْ","translation":"that they","occurences":["12:110"]},{"word":"قَدْ","translation":"certainly","occurences":["12:110"]},{"word":"كُذِبُوا۟","translation":"were denied","occurences":["12:110"]},{"word":"جَآءَهُمْ","translation":"then came to them","occurences":["12:110"]},{"word":"نَصْرُنَا","translation":"Our help","occurences":["12:110"]},{"word":"فَنُجِّىَ","translation":"and was saved","occurences":["12:110"]},{"word":"مَن","translation":"whom","occurences":["12:110"]},{"word":"نَّشَآءُ ۖ","translation":"We willed","occurences":["12:110"]},{"word":"وَلَا","translation":"And not","occurences":["12:110"]},{"word":"يُرَدُّ","translation":"(can) be repelled","occurences":["12:110"]},{"word":"بَأْسُنَا","translation":"Our punishment","occurences":["12:110"]},{"word":"عَنِ","translation":"from","occurences":["12:110"]},{"word":"ٱلْقَوْمِ","translation":"the people","occurences":["12:110"]},{"word":"ٱلْمُجْرِمِينَ","translation":"(who are) criminals","occurences":["12:110"]},{"word":"لَقَدْ","translation":"Verily","occurences":["12:111"]},{"word":"قَصَصِهِمْ","translation":"their stories","occurences":["12:111"]},{"word":"عِبْرَةٌۭ","translation":"a lesson","occurences":["12:111"]},{"word":"لِّأُو۟لِى","translation":"for men","occurences":["12:111"]},{"word":"ٱلْأَلْبَـٰبِ ۗ","translation":"(of) understanding","occurences":["12:111"]},{"word":"مَا","translation":"Not","occurences":["12:111"]},{"word":"حَدِيثًۭا","translation":"a narration","occurences":["12:111"]},{"word":"يُفْتَرَىٰ","translation":"invented","occurences":["12:111"]},{"word":"وَلَـٰكِن","translation":"but","occurences":["12:111"]},{"word":"تَصْدِيقَ","translation":"a confirmation","occurences":["12:111"]},{"word":"ٱلَّذِى","translation":"(of that) which","occurences":["12:111"]},{"word":"بَيْنَ","translation":"(was) before it","occurences":["12:111"]},{"word":"يَدَيْهِ","translation":"(was) before it","occurences":["12:111"]},{"word":"وَتَفْصِيلَ","translation":"and a detailed explanation","occurences":["12:111"]},{"word":"كُلِّ","translation":"(of) all","occurences":["12:111"]},{"word":"شَىْءٍۢ","translation":"things","occurences":["12:111"]},{"word":"وَهُدًۭى","translation":"and a guidance","occurences":["12:111"]},{"word":"وَرَحْمَةًۭ","translation":"and mercy","occurences":["12:111"]},{"word":"لِّقَوْمٍۢ","translation":"for a people","occurences":["12:111"]},{"word":"يُؤْمِنُونَ","translation":"who believe","occurences":["12:111"]}]