[{"word":"فَلَمَّا","translation":"Then when","occurences":["26:61"]},{"word":"تَرَٰٓءَا","translation":"saw each other","occurences":["26:61"]},{"word":"ٱلْجَمْعَانِ","translation":"the two hosts","occurences":["26:61"]},{"word":"قَالَ","translation":"said","occurences":["26:61","26:62","26:70","26:72","26:75"]},{"word":"أَصْحَـٰبُ","translation":"(the) companions","occurences":["26:61"]},{"word":"مُوسَىٰٓ","translation":"(of) Musa","occurences":["26:61","26:63"]},{"word":"إِنَّا","translation":"Indeed, we","occurences":["26:61"]},{"word":"لَمُدْرَكُونَ","translation":"(are) surely to be overtaken","occurences":["26:61"]},{"word":"كَلَّآ ۖ","translation":"Nay","occurences":["26:62"]},{"word":"إِنَّ","translation":"indeed","occurences":["26:62","26:67"]},{"word":"مَعِىَ","translation":"with me","occurences":["26:62"]},{"word":"رَبِّى","translation":"(is) my Lord","occurences":["26:62"]},{"word":"سَيَهْدِينِ","translation":"He will guide me","occurences":["26:62"]},{"word":"فَأَوْحَيْنَآ","translation":"Then We inspired","occurences":["26:63"]},{"word":"إِلَىٰ","translation":"to","occurences":["26:63"]},{"word":"أَنِ","translation":"[that]","occurences":["26:63"]},{"word":"ٱضْرِب","translation":"Strike","occurences":["26:63"]},{"word":"بِّعَصَاكَ","translation":"with your staff","occurences":["26:63"]},{"word":"ٱلْبَحْرَ ۖ","translation":"the sea","occurences":["26:63"]},{"word":"فَٱنفَلَقَ","translation":"So it parted","occurences":["26:63"]},{"word":"فَكَانَ","translation":"and became","occurences":["26:63"]},{"word":"كُلُّ","translation":"each","occurences":["26:63"]},{"word":"فِرْقٍۢ","translation":"part","occurences":["26:63"]},{"word":"كَٱلطَّوْدِ","translation":"like the mountain","occurences":["26:63"]},{"word":"ٱلْعَظِيمِ","translation":"[the] great","occurences":["26:63"]},{"word":"وَأَزْلَفْنَا","translation":"And We brought near","occurences":["26:64"]},{"word":"ثَمَّ","translation":"there","occurences":["26:64"]},{"word":"ٱلْـَٔاخَرِينَ","translation":"the others","occurences":["26:64","26:66"]},{"word":"وَأَنجَيْنَا","translation":"And We saved","occurences":["26:65"]},{"word":"مُوسَىٰ","translation":"Musa","occurences":["26:65"]},{"word":"وَمَن","translation":"and who","occurences":["26:65"]},{"word":"مَّعَهُۥٓ","translation":"(were) with him","occurences":["26:65"]},{"word":"أَجْمَعِينَ","translation":"all","occurences":["26:65"]},{"word":"ثُمَّ","translation":"Then","occurences":["26:66","26:81"]},{"word":"أَغْرَقْنَا","translation":"We drowned","occurences":["26:66"]},{"word":"فِى","translation":"in","occurences":["26:67"]},{"word":"ذَٰلِكَ","translation":"that","occurences":["26:67"]},{"word":"لَـَٔايَةًۭ ۖ","translation":"surely (is) a Sign","occurences":["26:67"]},{"word":"وَمَا","translation":"but not","occurences":["26:67"]},{"word":"كَانَ","translation":"are","occurences":["26:67"]},{"word":"أَكْثَرُهُم","translation":"most of them","occurences":["26:67"]},{"word":"مُّؤْمِنِينَ","translation":"believers","occurences":["26:67"]},{"word":"وَإِنَّ","translation":"And indeed","occurences":["26:68"]},{"word":"رَبَّكَ","translation":"your Lord","occurences":["26:68"]},{"word":"لَهُوَ","translation":"surely He","occurences":["26:68"]},{"word":"ٱلْعَزِيزُ","translation":"(is) the All-Mighty","occurences":["26:68"]},{"word":"ٱلرَّحِيمُ","translation":"the Most Merciful","occurences":["26:68"]},{"word":"وَٱتْلُ","translation":"And recite","occurences":["26:69"]},{"word":"عَلَيْهِمْ","translation":"to them","occurences":["26:69"]},{"word":"نَبَأَ","translation":"(the) news","occurences":["26:69"]},{"word":"إِبْرَٰهِيمَ","translation":"(of) Ibrahim","occurences":["26:69"]},{"word":"إِذْ","translation":"When","occurences":["26:70","26:72"]},{"word":"لِأَبِيهِ","translation":"to his father","occurences":["26:70"]},{"word":"وَقَوْمِهِۦ","translation":"and his people","occurences":["26:70"]},{"word":"مَا","translation":"What","occurences":["26:70"]},{"word":"تَعْبُدُونَ","translation":"(do) you worship","occurences":["26:70","26:75"]},{"word":"قَالُوا۟","translation":"They said","occurences":["26:71","26:74"]},{"word":"نَعْبُدُ","translation":"We worship","occurences":["26:71"]},{"word":"أَصْنَامًۭا","translation":"idols","occurences":["26:71"]},{"word":"فَنَظَلُّ","translation":"so we will remain","occurences":["26:71"]},{"word":"لَهَا","translation":"to them","occurences":["26:71"]},{"word":"عَـٰكِفِينَ","translation":"devoted","occurences":["26:71"]},{"word":"هَلْ","translation":"Do","occurences":["26:72"]},{"word":"يَسْمَعُونَكُمْ","translation":"they hear you","occurences":["26:72"]},{"word":"تَدْعُونَ","translation":"you call","occurences":["26:72"]},{"word":"أَوْ","translation":"Or","occurences":["26:73","26:73"]},{"word":"يَنفَعُونَكُمْ","translation":"(do) they benefit you","occurences":["26:73"]},{"word":"يَضُرُّونَ","translation":"they harm (you)","occurences":["26:73"]},{"word":"بَلْ","translation":"Nay","occurences":["26:74"]},{"word":"وَجَدْنَآ","translation":"but we found","occurences":["26:74"]},{"word":"ءَابَآءَنَا","translation":"our forefathers","occurences":["26:74"]},{"word":"كَذَٰلِكَ","translation":"like that ","occurences":["26:74"]},{"word":"يَفْعَلُونَ","translation":"doing","occurences":["26:74"]},{"word":"أَفَرَءَيْتُم","translation":"Do you see","occurences":["26:75"]},{"word":"مَّا","translation":"what","occurences":["26:75"]},{"word":"كُنتُمْ","translation":"you have been","occurences":["26:75"]},{"word":"أَنتُمْ","translation":"You","occurences":["26:76"]},{"word":"وَءَابَآؤُكُمُ","translation":"and your forefathers","occurences":["26:76"]},{"word":"ٱلْأَقْدَمُونَ","translation":"and your forefathers","occurences":["26:76"]},{"word":"فَإِنَّهُمْ","translation":"Indeed, they","occurences":["26:77"]},{"word":"عَدُوٌّۭ","translation":"(are) enemies","occurences":["26:77"]},{"word":"لِّىٓ","translation":"to me","occurences":["26:77"]},{"word":"إِلَّا","translation":"except","occurences":["26:77"]},{"word":"رَبَّ","translation":"(the) Lord","occurences":["26:77"]},{"word":"ٱلْعَـٰلَمِينَ","translation":"(of) the worlds","occurences":["26:77"]},{"word":"ٱلَّذِى","translation":"The One Who","occurences":["26:78"]},{"word":"خَلَقَنِى","translation":"created me","occurences":["26:78"]},{"word":"فَهُوَ","translation":"and He","occurences":["26:78","26:80"]},{"word":"يَهْدِينِ","translation":"guides me","occurences":["26:78"]},{"word":"وَٱلَّذِى","translation":"And the One Who","occurences":["26:79","26:81"]},{"word":"هُوَ","translation":"[He]","occurences":["26:79"]},{"word":"يُطْعِمُنِى","translation":"gives me food","occurences":["26:79"]},{"word":"وَيَسْقِينِ","translation":"and gives me drink","occurences":["26:79"]},{"word":"وَإِذَا","translation":"And when","occurences":["26:80"]},{"word":"مَرِضْتُ","translation":"I am ill","occurences":["26:80"]},{"word":"يَشْفِينِ","translation":"cures me","occurences":["26:80"]},{"word":"يُمِيتُنِى","translation":"will cause me to die","occurences":["26:81"]},{"word":"يُحْيِينِ","translation":"he will give me life","occurences":["26:81"]},{"word":"وَٱلَّذِىٓ","translation":"And the One Who ","occurences":["26:82"]},{"word":"أَطْمَعُ","translation":"I hope","occurences":["26:82"]},{"word":"أَن","translation":"that","occurences":["26:82"]},{"word":"يَغْفِرَ","translation":"He will forgive","occurences":["26:82"]},{"word":"لِى","translation":"for me","occurences":["26:82","26:83"]},{"word":"خَطِيٓـَٔتِى","translation":"my faults","occurences":["26:82"]},{"word":"يَوْمَ","translation":"(on the) Day","occurences":["26:82"]},{"word":"ٱلدِّينِ","translation":"(of) the Judgment","occurences":["26:82"]},{"word":"رَبِّ","translation":"My Lord","occurences":["26:83"]},{"word":"هَبْ","translation":"Grant","occurences":["26:83"]},{"word":"حُكْمًۭا","translation":"wisdom","occurences":["26:83"]},{"word":"وَأَلْحِقْنِى","translation":"and join me","occurences":["26:83"]},{"word":"بِٱلصَّـٰلِحِينَ","translation":"with the righteous","occurences":["26:83"]}]